Workbook

Sheet README
A1: Momentra iPhone Physical Device + Backend Load Test Workbook
A2: Purpose | B2: Source of truth for Maestro-driven Android/iPhone input, backend load observation, and calculation reconciliation.
A3: Dataset | B3: 3,500 valid transactions: 1,167 Personal + 1,167 Group + 1,166 Business.
A4: Load strategy | B4: Transactions are interleaved Personal -> Group -> Business throughout a single-platform 3,500-row certification run.
A5: Devices | B5: Platform-isolated dataset: iPhone only. Use separate QA_* identities from the other platform.
A6: Correctness | B6: Expected_Summary and Group_Splits contain the expected totals/splits. Reconciliation is for pasted actual app/backend values.
A7: Performance | B7: Performance_Log includes checkpoints through 3,300 rows and formulas for degradation/error thresholds.
A8: Figma note | B8: QuickAdd labels in QuickAdd_Catalog are representative placeholders and marked CONFIRM_FROM_FIGMA because the Figma connector did not return readable labels in this session. Replace labels there/Transactions before final Maestro automation if exact UI text differs.
A9: Recommended execution | B9: Run 300-write pilot separately, then certify checkpoints at 100, 250, 500, 1,000, 1,500, 2,000, 2,500, 3,000, 3,100, 3,200, 3,300, 3,400, 3,500.
A10: Important | B10: Main dataset contains only valid writes. Negative/invalid/idempotency/concurrency cases remain in Test_Cases.

Sheet Config
A1: Setting | B1: Value | C1: Notes
A2: Random Seed | B2: 20260903 | C2: Deterministic generation
A3: Total Transactions | B3: 3500 | C3: Main valid dataset
A4: Personal Target | B4: 1167 | C4: Minimum requested 1000
A5: Group Target | B5: 1167 | C5: Minimum requested 1000
A6: Business Target | B6: 1166 | C6: Minimum requested 1000
A7: Currency | B7: INR | C7: Change if a test moment uses another currency
A8: Money Tolerance | B8: 0.01 | C8: PASS tolerance for reconciliation
A9: Starter Create p95 Threshold ms | B9: 2000 | C9: Editable test threshold, not a product SLA
A10: Starter Read/Refresh p95 Threshold ms | B10: 2000 | C10: Editable test threshold, not a product SLA
A11: Max p95 Degradation vs Baseline | B11: 0.3 | C11: Editable threshold
A12: Max Error Rate | B12: 0.01 | C12: Editable threshold

Sheet QuickAdd_Catalog
A1: Mode | B1: Family | C1: Moment | D1: Quick_Add | E1: Semantic_Type | F1: Figma_Verification | G1: Figma_Node | H1: Target_Txn_Count | I1: Notes
A2: Personal | B2: Personal | C2: Life Operations | D2: Groceries | E2: Expense | F2: CONFIRM_FROM_FIGMA | G2: 169:487 | H2: 275 | I2: Representative label; replace with exact UI text if different.
A3: Personal | B3: Personal | C3: Life Operations | D3: Rent | E3: Expense | F3: CONFIRM_FROM_FIGMA | G3: 169:487 | H3: 275 | I3: Representative label; replace with exact UI text if different.
A4: Personal | B4: Personal | C4: Life Operations | D4: Bills | E4: Expense | F4: CONFIRM_FROM_FIGMA | G4: 169:487 | H4: 275 | I4: Representative label; replace with exact UI text if different.
A5: Personal | B5: Personal | C5: Life Operations | D5: Transport | E5: Expense | F5: CONFIRM_FROM_FIGMA | G5: 169:487 | H5: 275 | I5: Representative label; replace with exact UI text if different.
A6: Personal | B6: Personal | C6: Life Operations | D6: Healthcare | E6: Expense | F6: CONFIRM_FROM_FIGMA | G6: 169:487 | H6: 275 | I6: Representative label; replace with exact UI text if different.
A7: Personal | B7: Personal | C7: Life Operations | D7: Subscriptions | E7: Expense | F7: CONFIRM_FROM_FIGMA | G7: 169:487 | H7: 275 | I7: Representative label; replace with exact UI text if different.
A8: Personal | B8: Personal | C8: Life Operations | D8: Repairs | E8: Expense | F8: CONFIRM_FROM_FIGMA | G8: 169:487 | H8: 275 | I8: Representative label; replace with exact UI text if different.
A9: Personal | B9: Personal | C9: Future Building | D9: Savings | E9: Transfer | F9: CONFIRM_FROM_FIGMA | G9: 169:487 | H9: 275 | I9: Representative label; replace with exact UI text if different.
A10: Personal | B10: Personal | C10: Future Building | D10: Emergency Fund | E10: Transfer | F10: CONFIRM_FROM_FIGMA | G10: 169:487 | H10: 275 | I10: Representative label; replace with exact UI text if different.
A11: Personal | B11: Personal | C11: Future Building | D11: Investments | E11: Investment | F11: CONFIRM_FROM_FIGMA | G11: 169:487 | H11: 275 | I11: Representative label; replace with exact UI text if different.
A12: Personal | B12: Personal | C12: Future Building | D12: Education | E12: Expense | F12: CONFIRM_FROM_FIGMA | G12: 169:487 | H12: 275 | I12: Representative label; replace with exact UI text if different.
A13: Personal | B13: Personal | C13: Future Building | D13: Goal Contribution | E13: Transfer | F13: CONFIRM_FROM_FIGMA | G13: 169:487 | H13: 275 | I13: Representative label; replace with exact UI text if different.
... A103: Business | B103: Business | C103: Business Operations | D103: Tax | E103: Expense | F103: CONFIRM_FROM_FIGMA | G103: 169:487 | H103: 366 | I103: Representative label; replace with exact UI text if different.

Sheet Members
A1: Context | B1: Member_ID | C1: Display_Name | D1: Role | E1: Use_In_Test
A2: Personal | B2: IOS-MEM-01 | C2: IOS Santosh | D2: OWNER | E2: YES
A3: Group | B3: IOS-MEM-02 | C3: IOS Santosh | D3: OWNER | E3: YES
A4: Group | B4: IOS-MEM-03 | C4: IOS Aarav | D4: MEMBER | E4: YES
A5: Group | B5: IOS-MEM-04 | C5: IOS Meera | D5: MEMBER | E5: YES
A6: Group | B6: IOS-MEM-05 | C6: IOS Rohan | D6: MEMBER | E6: YES
A7: Group | B7: IOS-MEM-06 | C7: IOS Isha | D7: MEMBER | E7: YES
A8: Group | B8: IOS-MEM-07 | C8: IOS Vikram | D8: MEMBER | E8: YES
A9: Business | B9: IOS-MEM-08 | C9: IOS Santosh | D9: OWNER | E9: YES
A10: Business | B10: IOS-MEM-09 | C10: IOS Ops Admin | D10: ADMIN | E10: YES
A11: Business | B11: IOS-MEM-10 | C11: IOS Finance Lead | D11: ADMIN | E11: YES
A12: Business | B12: IOS-MEM-11 | C12: IOS Team Member | D12: MEMBER | E12: YES

Sheet Transactions
A1: Sequence | B1: Txn_ID | C1: Mode | D1: Family | E1: Moment | F1: Quick_Add | G1: Semantic_Type | H1: Txn_Date | I1: Txn_Time | J1: Timestamp | K1: Amount | L1: Currency | M1: Expected_Signed_Amount | N1: Paid_By | O1: Participant_Count | P1: Split_Method | Q1: Description | R1: Device_Target | S1: Run_Batch | T1: Backend_Load_Band | U1: Expected_Status | V1: Idempotency_Key
A2: 1 | B2: MTR-IOS-0001 | C2: Personal | D2: Personal | E2: Life Operations | F2: Groceries | G2: Expense | H2: 46042 | I2: 0.23650463 | J2: 46042.237 | K2: 14066.5 | L2: INR | M2: -14066.5 | N2: IOS Owner | Q2: MAESTRO-IOS-PERSONAL-LIFE_OPERATIONS-0001 | Groceries | 14066.50 | R2: iPhone | S2: B01 | T2: BASELINE_1_500 | U2: CREATED | V2: idem-20260902-ios-0001
A3: 2 | B3: MTR-IOS-0002 | C3: Group | D3: Shared Experience | E3: Trip | F3: Travel | G3: Expense | H3: 46023 | I3: 0.73158565 | J3: 46023.732 | K3: 26868.32 | L3: INR | M3: -26868.32 | N3: IOS Owner | O3: 3 | P3: EQUAL | Q3: MAESTRO-IOS-GROUP-TRIP-0002 | Travel | 26868.32 | R3: iPhone | S3: B01 | T3: BASELINE_1_500 | U3: CREATED | V3: idem-20260902-ios-0002
A4: 3 | B4: MTR-IOS-0003 | C4: Business | D4: Business | E4: Team Operations | F4: Payroll | G4: Expense | H4: 46131 | I4: 0.50604167 | J4: 46131.506 | K4: 57453.63 | L4: INR | M4: -57453.63 | N4: IOS Owner | Q4: MAESTRO-IOS-BUSINESS-TEAM_OPERATIONS-0003 | Payroll | 57453.63 | R4: iPhone | S4: B01 | T4: BASELINE_1_500 | U4: CREATED | V4: idem-20260902-ios-0003
A5: 4 | B5: MTR-IOS-0004 | C5: Personal | D5: Personal | E5: Life Operations | F5: Rent | G5: Expense | H5: 46167 | I5: 0.18815972 | J5: 46167.188 | K5: 2414.9 | L5: INR | M5: -2414.9 | N5: IOS Owner | Q5: MAESTRO-IOS-PERSONAL-LIFE_OPERATIONS-0004 | Rent | 2414.90 | R5: iPhone | S5: B01 | T5: BASELINE_1_500 | U5: CREATED | V5: idem-20260902-ios-0004
A6: 5 | B6: MTR-IOS-0005 | C6: Group | D6: Shared Experience | E6: Trip | F6: Stay | G6: Expense | H6: 46231 | I6: 0.34469907 | J6: 46231.345 | K6: 18351.21 | L6: INR | M6: -18351.21 | N6: IOS Aarav | O6: 3 | P6: PERCENTAGE | Q6: MAESTRO-IOS-GROUP-TRIP-0005 | Stay | 18351.21 | R6: iPhone | S6: B01 | T6: BASELINE_1_500 | U6: CREATED | V6: idem-20260902-ios-0005
A7: 6 | B7: MTR-IOS-0006 | C7: Business | D7: Business | E7: Team Operations | F7: Contractor | G7: Expense | H7: 45913 | I7: 0.41313657 | J7: 45913.413 | K7: 109737.08 | L7: INR | M7: -109737.08 | N7: IOS Owner | Q7: MAESTRO-IOS-BUSINESS-TEAM_OPERATIONS-0006 | Contractor | 109737.08 | R7: iPhone | S7: B01 | T7: BASELINE_1_500 | U7: CREATED | V7: idem-20260902-ios-0006
A8: 7 | B8: MTR-IOS-0007 | C8: Personal | D8: Personal | E8: Life Operations | F8: Bills | G8: Expense | H8: 46044 | I8: 0.10094907 | J8: 46044.101 | K8: 7285.65 | L8: INR | M8: -7285.65 | N8: IOS Owner | Q8: MAESTRO-IOS-PERSONAL-LIFE_OPERATIONS-0007 | Bills | 7285.65 | R8: iPhone | S8: B01 | T8: BASELINE_1_500 | U8: CREATED | V8: idem-20260902-ios-0007
A9: 8 | B9: MTR-IOS-0008 | C9: Group | D9: Shared Experience | E9: Trip | F9: Food | G9: Expense | H9: 45963 | I9: 0.39880787 | J9: 45963.399 | K9: 25422.15 | L9: INR | M9: -25422.15 | N9: IOS Meera | O9: 3 | P9: EXACT | Q9: MAESTRO-IOS-GROUP-TRIP-0008 | Food | 25422.15 | R9: iPhone | S9: B01 | T9: BASELINE_1_500 | U9: CREATED | V9: idem-20260902-ios-0008
A10: 9 | B10: MTR-IOS-0009 | C10: Business | D10: Business | E10: Team Operations | F10: Hiring | G10: Expense | H10: 45990 | I10: 0.35172454 | J10: 45990.352 | K10: 142974.65 | L10: INR | M10: -142974.65 | N10: IOS Owner | Q10: MAESTRO-IOS-BUSINESS-TEAM_OPERATIONS-0009 | Hiring | 142974.65 | R10: iPhone | S10: B01 | T10: BASELINE_1_500 | U10: CREATED | V10: idem-20260902-ios-0009
A11: 10 | B11: MTR-IOS-0010 | C11: Personal | D11: Personal | E11: Life Operations | F11: Transport | G11: Expense | H11: 45975 | I11: 0.913125 | J11: 45975.913 | K11: 13838.38 | L11: INR | M11: -13838.38 | N11: IOS Owner | Q11: MAESTRO-IOS-PERSONAL-LIFE_OPERATIONS-0010 | Transport | 13838.38 | R11: iPhone | S11: B01 | T11: BASELINE_1_500 | U11: CREATED | V11: idem-20260902-ios-0010
A12: 11 | B12: MTR-IOS-0011 | C12: Group | D12: Shared Experience | E12: Trip | F12: Local Transport | G12: Expense | H12: 46193 | I12: 0.053483796 | J12: 46193.053 | K12: 20814.45 | L12: INR | M12: -20814.45 | N12: IOS Owner | O12: 3 | P12: SHARES | Q12: MAESTRO-IOS-GROUP-TRIP-0011 | Local Transport | 20814.45 | R12: iPhone | S12: B01 | T12: BASELINE_1_500 | U12: CREATED | V12: idem-20260902-ios-0011
A13: 12 | B13: MTR-IOS-0012 | C13: Business | D13: Business | E13: Team Operations | F13: Team Meal | G13: Expense | H13: 45972 | I13: 0.72216435 | J13: 45972.722 | K13: 153816.21 | L13: INR | M13: -153816.21 | N13: IOS Owner | Q13: MAESTRO-IOS-BUSINESS-TEAM_OPERATIONS-0012 | Team Meal | 153816.21 | R13: iPhone | S13: B01 | T13: BASELINE_1_500 | U13: CREATED | V13: idem-20260902-ios-0012
A14: 13 | B14: MTR-IOS-0013 | C14: Personal | D14: Personal | E14: Life Operations | F14: Healthcare | G14: Expense | H14: 45970 | I14: 0.37262731 | J14: 45970.373 | K14: 12883.33 | L14: INR | M14: -12883.33 | N14: IOS Owner | Q14: MAESTRO-IOS-PERSONAL-LIFE_OPERATIONS-0013 | Healthcare | 12883.33 | R14: iPhone | S14: B01 | T14: BASELINE_1_500 | U14: CREATED | V14: idem-20260902-ios-0013
A15: 14 | B15: MTR-IOS-0014 | C15: Group | D15: Shared Experience | E15: Trip | F15: Activities | G15: Expense | H15: 46176 | I15: 0.03525463 | J15: 46176.035 | K15: 8585.78 | L15: INR | M15: -8585.78 | N15: IOS Aarav | O15: 3 | P15: EQUAL | Q15: MAESTRO-IOS-GROUP-TRIP-0014 | Activities | 8585.78 | R15: iPhone | S15: B01 | T15: BASELINE_1_500 | U15: CREATED | V15: idem-20260902-ios-0014
A16: 15 | B16: MTR-IOS-0015 | C16: Business | D16: Business | E16: Team Operations | F16: Travel | G16: Expense | H16: 46115 | I16: 0.20310185 | J16: 46115.203 | K16: 126238.94 | L16: INR | M16: -126238.94 | N16: IOS Owner | Q16: MAESTRO-IOS-BUSINESS-TEAM_OPERATIONS-0015 | Travel | 126238.94 | R16: iPhone | S16: B01 | T16: BASELINE_1_500 | U16: CREATED | V16: idem-20260902-ios-0015
A17: 16 | B17: MTR-IOS-0016 | C17: Personal | D17: Personal | E17: Life Operations | F17: Subscriptions | G17: Expense | H17: 46010 | I17: 0.6559375 | J17: 46010.656 | K17: 12564.33 | L17: INR | M17: -12564.33 | N17: IOS Owner | Q17: MAESTRO-IOS-PERSONAL-LIFE_OPERATIONS-0016 | Subscriptions | 12564.33 | R17: iPhone | S17: B01 | T17: BASELINE_1_500 | U17: CREATED | V17: idem-20260902-ios-0016
A18: 17 | B18: MTR-IOS-0017 | C18: Group | D18: Shared Experience | E18: Trip | F18: Shopping | G18: Expense | H18: 46216 | I18: 0.7216088 | J18: 46216.722 | K18: 14891.49 | L18: INR | M18: -14891.49 | N18: IOS Meera | O18: 3 | P18: PERCENTAGE | Q18: MAESTRO-IOS-GROUP-TRIP-0017 | Shopping | 14891.49 | R18: iPhone | S18: B01 | T18: BASELINE_1_500 | U18: CREATED | V18: idem-20260902-ios-0017
A19: 18 | B19: MTR-IOS-0018 | C19: Business | D19: Business | E19: Team Operations | F19: Training | G19: Expense | H19: 45997 | I19: 0.89090278 | J19: 45997.891 | K19: 77896.48 | L19: INR | M19: -77896.48 | N19: IOS Owner | Q19: MAESTRO-IOS-BUSINESS-TEAM_OPERATIONS-0018 | Training | 77896.48 | R19: iPhone | S19: B01 | T19: BASELINE_1_500 | U19: CREATED | V19: idem-20260902-ios-0018
A20: 19 | B20: MTR-IOS-0019 | C20: Personal | D20: Personal | E20: Life Operations | F20: Repairs | G20: Expense | H20: 46026 | I20: 0.53804398 | J20: 46026.538 | K20: 17848.59 | L20: INR | M20: -17848.59 | N20: IOS Owner | Q20: MAESTRO-IOS-PERSONAL-LIFE_OPERATIONS-0019 | Repairs | 17848.59 | R20: iPhone | S20: B01 | T20: BASELINE_1_500 | U20: CREATED | V20: idem-20260902-ios-0019
A21: 20 | B21: MTR-IOS-0020 | C21: Group | D21: Shared Experience | E21: Trip | F21: Other | G21: Expense | H21: 46213 | I21: 0.11194444 | J21: 46213.112 | K21: 16125.67 | L21: INR | M21: -16125.67 | N21: IOS Owner | O21: 3 | P21: EXACT | Q21: MAESTRO-IOS-GROUP-TRIP-0020 | Other | 16125.67 | R21: iPhone | S21: B01 | T21: BASELINE_1_500 | U21: CREATED | V21: idem-20260902-ios-0020
A22: 21 | B22: MTR-IOS-0021 | C22: Business | D22: Business | E22: Team Operations | F22: Tools | G22: Expense | H22: 46264 | I22: 0.87739583 | J22: 46264.877 | K22: 135446.27 | L22: INR | M22: -135446.27 | N22: IOS Owner | Q22: MAESTRO-IOS-BUSINESS-TEAM_OPERATIONS-0021 | Tools | 135446.27 | R22: iPhone | S22: B01 | T22: BASELINE_1_500 | U22: CREATED | V22: idem-20260902-ios-0021
A23: 22 | B23: MTR-IOS-0022 | C23: Personal | D23: Personal | E23: Future Building | F23: Savings | G23: Transfer | H23: 46252 | I23: 0.5221875 | J23: 46252.522 | K23: 16827.67 | L23: INR | M23: 0 | N23: IOS Owner | Q23: MAESTRO-IOS-PERSONAL-FUTURE_BUILDING-0022 | Savings | 16827.67 | R23: iPhone | S23: B01 | T23: BASELINE_1_500 | U23: CREATED | V23: idem-20260902-ios-0022
A24: 23 | B24: MTR-IOS-0023 | C24: Group | D24: Shared Experience | E24: Wedding | F24: Venue | G24: Expense | H24: 46174 | I24: 0.86997685 | J24: 46174.87 | K24: 24925.16 | L24: INR | M24: -24925.16 | N24: IOS Aarav | O24: 3 | P24: SHARES | Q24: MAESTRO-IOS-GROUP-WEDDING-0023 | Venue | 24925.16 | R24: iPhone | S24: B01 | T24: BASELINE_1_500 | U24: CREATED | V24: idem-20260902-ios-0023
A25: 24 | B25: MTR-IOS-0024 | C25: Business | D25: Business | E25: Business Runway | F25: Funding | G25: Income | H25: 46013 | I25: 0.52298611 | J25: 46013.523 | K25: 121141.46 | L25: INR | M25: 121141.46 | N25: IOS Owner | Q25: MAESTRO-IOS-BUSINESS-BUSINESS_RUNWAY-0024 | Funding | 121141.46 | R25: iPhone | S25: B01 | T25: BASELINE_1_500 | U25: CREATED | V25: idem-20260902-ios-0024
A26: 25 | B26: MTR-IOS-0025 | C26: Personal | D26: Personal | E26: Future Building | F26: Emergency Fund | G26: Transfer | H26: 45982 | I26: 0.12578704 | J26: 45982.126 | K26: 4005.71 | L26: INR | M26: 0 | N26: IOS Owner | Q26: MAESTRO-IOS-PERSONAL-FUTURE_BUILDING-0025 | Emergency Fund | 4005.71 | R26: iPhone | S26: B01 | T26: BASELINE_1_500 | U26: CREATED | V26: idem-20260902-ios-0025
A27: 26 | B27: MTR-IOS-0026 | C27: Group | D27: Shared Experience | E27: Wedding | F27: Catering | G27: Expense | H27: 46186 | I27: 0.51579861 | J27: 46186.516 | K27: 19704.71 | L27: INR | M27: -19704.71 | N27: IOS Meera | O27: 3 | P27: EQUAL | Q27: MAESTRO-IOS-GROUP-WEDDING-0026 | Catering | 19704.71 | R27: iPhone | S27: B01 | T27: BASELINE_1_500 | U27: CREATED | V27: idem-20260902-ios-0026
A28: 27 | B28: MTR-IOS-0027 | C28: Business | D28: Business | E28: Business Runway | F28: Revenue | G28: Income | H28: 45994 | I28: 0.25048611 | J28: 45994.25 | K28: 144069.9 | L28: INR | M28: 144069.9 | N28: IOS Owner | Q28: MAESTRO-IOS-BUSINESS-BUSINESS_RUNWAY-0027 | Revenue | 144069.90 | R28: iPhone | S28: B01 | T28: BASELINE_1_500 | U28: CREATED | V28: idem-20260902-ios-0027
A29: 28 | B29: MTR-IOS-0028 | C29: Personal | D29: Personal | E29: Future Building | F29: Investments | G29: Investment | H29: 45934 | I29: 0.94447917 | J29: 45934.944 | K29: 4161.04 | L29: INR | M29: 0 | N29: IOS Owner | Q29: MAESTRO-IOS-PERSONAL-FUTURE_BUILDING-0028 | Investments | 4161.04 | R29: iPhone | S29: B01 | T29: BASELINE_1_500 | U29: CREATED | V29: idem-20260902-ios-0028
A30: 29 | B30: MTR-IOS-0029 | C30: Group | D30: Shared Experience | E30: Wedding | F30: Decor | G30: Expense | H30: 46113 | I30: 0.66913194 | J30: 46113.669 | K30: 15620.75 | L30: INR | M30: -15620.75 | N30: IOS Owner | O30: 3 | P30: PERCENTAGE | Q30: MAESTRO-IOS-GROUP-WEDDING-0029 | Decor | 15620.75 | R30: iPhone | S30: B01 | T30: BASELINE_1_500 | U30: CREATED | V30: idem-20260902-ios-0029
A31: 30 | B31: MTR-IOS-0030 | C31: Business | D31: Business | E31: Business Runway | F31: Burn | G31: Expense | H31: 46170 | I31: 0.34246528 | J31: 46170.342 | K31: 142385.1 | L31: INR | M31: -142385.1 | N31: IOS Owner | Q31: MAESTRO-IOS-BUSINESS-BUSINESS_RUNWAY-0030 | Burn | 142385.10 | R31: iPhone | S31: B01 | T31: BASELINE_1_500 | U31: CREATED | V31: idem-20260902-ios-0030
A32: 31 | B32: MTR-IOS-0031 | C32: Personal | D32: Personal | E32: Future Building | F32: Education | G32: Expense | H32: 45931 | I32: 0.94459491 | J32: 45931.945 | K32: 6294.62 | L32: INR | M32: -6294.62 | N32: IOS Owner | Q32: MAESTRO-IOS-PERSONAL-FUTURE_BUILDING-0031 | Education | 6294.62 | R32: iPhone | S32: B01 | T32: BASELINE_1_500 | U32: CREATED | V32: idem-20260902-ios-0031
A33: 32 | B33: MTR-IOS-0032 | C33: Group | D33: Shared Experience | E33: Wedding | F33: Travel | G33: Expense | H33: 45999 | I33: 0.11041667 | J33: 45999.11 | K33: 16472.62 | L33: INR | M33: -16472.62 | N33: IOS Aarav | O33: 3 | P33: EXACT | Q33: MAESTRO-IOS-GROUP-WEDDING-0032 | Travel | 16472.62 | R33: iPhone | S33: B01 | T33: BASELINE_1_500 | U33: CREATED | V33: idem-20260902-ios-0032
A34: 33 | B34: MTR-IOS-0033 | C34: Business | D34: Business | E34: Business Runway | F34: Reserve | G34: Transfer | H34: 46079 | I34: 0.51417824 | J34: 46079.514 | K34: 827.54 | L34: INR | M34: 0 | N34: IOS Owner | Q34: MAESTRO-IOS-BUSINESS-BUSINESS_RUNWAY-0033 | Reserve | 827.54 | R34: iPhone | S34: B01 | T34: BASELINE_1_500 | U34: CREATED | V34: idem-20260902-ios-0033
A35: 34 | B35: MTR-IOS-0034 | C35: Personal | D35: Personal | E35: Future Building | F35: Goal Contribution | G35: Transfer | H35: 46192 | I35: 0.14359954 | J35: 46192.144 | K35: 10116.79 | L35: INR | M35: 0 | N35: IOS Owner | Q35: MAESTRO-IOS-PERSONAL-FUTURE_BUILDING-0034 | Goal Contribution | 10116.79 | R35: iPhone | S35: B01 | T35: BASELINE_1_500 | U35: CREATED | V35: idem-20260902-ios-0034
A36: 35 | B36: MTR-IOS-0035 | C36: Group | D36: Shared Experience | E36: Wedding | F36: Gifts | G36: Expense | H36: 45984 | I36: 0.15180556 | J36: 45984.152 | K36: 18821.96 | L36: INR | M36: -18821.96 | N36: IOS Meera | O36: 3 | P36: SHARES | Q36: MAESTRO-IOS-GROUP-WEDDING-0035 | Gifts | 18821.96 | R36: iPhone | S36: B01 | T36: BASELINE_1_500 | U36: CREATED | V36: idem-20260902-ios-0035
A37: 36 | B37: MTR-IOS-0036 | C37: Business | D37: Business | E37: Business Runway | F37: Loan | G37: Income | H37: 46087 | I37: 0.99681713 | J37: 46087.997 | K37: 122441.2 | L37: INR | M37: 122441.2 | N37: IOS Owner | Q37: MAESTRO-IOS-BUSINESS-BUSINESS_RUNWAY-0036 | Loan | 122441.20 | R37: iPhone | S37: B01 | T37: BASELINE_1_500 | U37: CREATED | V37: idem-20260902-ios-0036
A38: 37 | B38: MTR-IOS-0037 | C38: Personal | D38: Personal | E38: Lifestyle | F38: Dining | G38: Expense | H38: 46118 | I38: 0.72484954 | J38: 46118.725 | K38: 1 | L38: INR | M38: -1 | N38: IOS Owner | Q38: MAESTRO-IOS-PERSONAL-LIFESTYLE-0037 | Dining | 1.00 | R38: iPhone | S38: B01 | T38: BASELINE_1_500 | U38: CREATED | V38: idem-20260902-ios-0037
A39: 38 | B39: MTR-IOS-0038 | C39: Group | D39: Shared Experience | E39: Wedding | F39: Photography | G39: Expense | H39: 46108 | I39: 0.088055556 | J39: 46108.088 | K39: 6824.65 | L39: INR | M39: -6824.65 | N39: IOS Owner | O39: 3 | P39: EQUAL | Q39: MAESTRO-IOS-GROUP-WEDDING-0038 | Photography | 6824.65 | R39: iPhone | S39: B01 | T39: BASELINE_1_500 | U39: CREATED | V39: idem-20260902-ios-0038
A40: 39 | B40: MTR-IOS-0039 | C40: Business | D40: Business | E40: Business Runway | F40: Investment | G40: Income | H40: 46231 | I40: 0.68909722 | J40: 46231.689 | K40: 161177.11 | L40: INR | M40: 161177.11 | N40: IOS Owner | Q40: MAESTRO-IOS-BUSINESS-BUSINESS_RUNWAY-0039 | Investment | 161177.11 | R40: iPhone | S40: B01 | T40: BASELINE_1_500 | U40: CREATED | V40: idem-20260902-ios-0039
A41: 40 | B41: MTR-IOS-0040 | C41: Personal | D41: Personal | E41: Lifestyle | F41: Shopping | G41: Expense | H41: 46198 | I41: 0.93106481 | J41: 46198.931 | K41: 8933.08 | L41: INR | M41: -8933.08 | N41: IOS Owner | Q41: MAESTRO-IOS-PERSONAL-LIFESTYLE-0040 | Shopping | 8933.08 | R41: iPhone | S41: B01 | T41: BASELINE_1_500 | U41: CREATED | V41: idem-20260902-ios-0040
A42: 41 | B42: MTR-IOS-0041 | C42: Group | D42: Shared Experience | E42: Wedding | F42: Other | G42: Expense | H42: 45956 | I42: 0.57467593 | J42: 45956.575 | K42: 18392.39 | L42: INR | M42: -18392.39 | N42: IOS Aarav | O42: 3 | P42: PERCENTAGE | Q42: MAESTRO-IOS-GROUP-WEDDING-0041 | Other | 18392.39 | R42: iPhone | S42: B01 | T42: BASELINE_1_500 | U42: CREATED | V42: idem-20260902-ios-0041
A43: 42 | B43: MTR-IOS-0042 | C43: Business | D43: Business | E43: Business Operations | F43: Software | G43: Expense | H43: 46127 | I43: 0.56552083 | J43: 46127.566 | K43: 31212.26 | L43: INR | M43: -31212.26 | N43: IOS Owner | Q43: MAESTRO-IOS-BUSINESS-BUSINESS_OPERATIONS-0042 | Software | 31212.26 | R43: iPhone | S43: B01 | T43: BASELINE_1_500 | U43: CREATED | V43: idem-20260902-ios-0042
A44: 43 | B44: MTR-IOS-0043 | C44: Personal | D44: Personal | E44: Lifestyle | F44: Entertainment | G44: Expense | H44: 45998 | I44: 0.19228009 | J44: 45998.192 | K44: 3405.74 | L44: INR | M44: -3405.74 | N44: IOS Owner | Q44: MAESTRO-IOS-PERSONAL-LIFESTYLE-0043 | Entertainment | 3405.74 | R44: iPhone | S44: B01 | T44: BASELINE_1_500 | U44: CREATED | V44: idem-20260902-ios-0043
A45: 44 | B45: MTR-IOS-0044 | C45: Group | D45: Shared Experience | E45: Office Outing | F45: Food | G45: Expense | H45: 46158 | I45: 0.2019213 | J45: 46158.202 | K45: 24075.67 | L45: INR | M45: -24075.67 | N45: IOS Meera | O45: 3 | P45: EXACT | Q45: MAESTRO-IOS-GROUP-OFFICE_OUTING-0044 | Food | 24075.67 | R45: iPhone | S45: B01 | T45: BASELINE_1_500 | U45: CREATED | V45: idem-20260902-ios-0044
A46: 45 | B46: MTR-IOS-0045 | C46: Business | D46: Business | E46: Business Operations | F46: Rent | G46: Expense | H46: 46054 | I46: 0.75994213 | J46: 46054.76 | K46: 115020.15 | L46: INR | M46: -115020.15 | N46: IOS Owner | Q46: MAESTRO-IOS-BUSINESS-BUSINESS_OPERATIONS-0045 | Rent | 115020.15 | R46: iPhone | S46: B01 | T46: BASELINE_1_500 | U46: CREATED | V46: idem-20260902-ios-0045
A47: 46 | B47: MTR-IOS-0046 | C47: Personal | D47: Personal | E47: Lifestyle | F47: Travel | G47: Expense | H47: 46166 | I47: 0.044930556 | J47: 46166.045 | K47: 2690.2 | L47: INR | M47: -2690.2 | N47: IOS Owner | Q47: MAESTRO-IOS-PERSONAL-LIFESTYLE-0046 | Travel | 2690.20 | R47: iPhone | S47: B01 | T47: BASELINE_1_500 | U47: CREATED | V47: idem-20260902-ios-0046
A48: 47 | B48: MTR-IOS-0047 | C48: Group | D48: Shared Experience | E48: Office Outing | F48: Travel | G48: Expense | H48: 46202 | I48: 0.39711806 | J48: 46202.397 | K48: 26939.54 | L48: INR | M48: -26939.54 | N48: IOS Owner | O48: 3 | P48: SHARES | Q48: MAESTRO-IOS-GROUP-OFFICE_OUTING-0047 | Travel | 26939.54 | R48: iPhone | S48: B01 | T48: BASELINE_1_500 | U48: CREATED | V48: idem-20260902-ios-0047
A49: 48 | B49: MTR-IOS-0048 | C49: Business | D49: Business | E49: Business Operations | F49: Marketing | G49: Expense | H49: 46092 | I49: 0.41083333 | J49: 46092.411 | K49: 13101.49 | L49: INR | M49: -13101.49 | N49: IOS Owner | Q49: MAESTRO-IOS-BUSINESS-BUSINESS_OPERATIONS-0048 | Marketing | 13101.49 | R49: iPhone | S49: B01 | T49: BASELINE_1_500 | U49: CREATED | V49: idem-20260902-ios-0048
A50: 49 | B50: MTR-IOS-0049 | C50: Personal | D50: Personal | E50: Lifestyle | F50: Fitness | G50: Expense | H50: 46188 | I50: 0.81461806 | J50: 46188.815 | K50: 11242.4 | L50: INR | M50: -11242.4 | N50: IOS Owner | Q50: MAESTRO-IOS-PERSONAL-LIFESTYLE-0049 | Fitness | 11242.40 | R50: iPhone | S50: B01 | T50: BASELINE_1_500 | U50: CREATED | V50: idem-20260902-ios-0049
A51: 50 | B51: MTR-IOS-0050 | C51: Group | D51: Shared Experience | E51: Office Outing | F51: Activities | G51: Expense | H51: 46149 | I51: 0.78572917 | J51: 46149.786 | K51: 23929.09 | L51: INR | M51: -23929.09 | N51: IOS Aarav | O51: 3 | P51: EQUAL | Q51: MAESTRO-IOS-GROUP-OFFICE_OUTING-0050 | Activities | 23929.09 | R51: iPhone | S51: B01 | T51: BASELINE_1_500 | U51: CREATED | V51: idem-20260902-ios-0050
A52: 51 | B52: MTR-IOS-0051 | C52: Business | D52: Business | E52: Business Operations | F52: Legal | G52: Expense | H52: 46144 | I52: 0.35462963 | J52: 46144.355 | K52: 129560.87 | L52: INR | M52: -129560.87 | N52: IOS Owner | Q52: MAESTRO-IOS-BUSINESS-BUSINESS_OPERATIONS-0051 | Legal | 129560.87 | R52: iPhone | S52: B02 | T52: BASELINE_1_500 | U52: CREATED | V52: idem-20260902-ios-0051
A53: 52 | B53: MTR-IOS-0052 | C53: Personal | D53: Personal | E53: Lifestyle | F53: Hobbies | G53: Expense | H53: 46125 | I53: 0.025555556 | J53: 46125.026 | K53: 12569.92 | L53: INR | M53: -12569.92 | N53: IOS Owner | Q53: MAESTRO-IOS-PERSONAL-LIFESTYLE-0052 | Hobbies | 12569.92 | R53: iPhone | S53: B02 | T53: BASELINE_1_500 | U53: CREATED | V53: idem-20260902-ios-0052
A54: 53 | B54: MTR-IOS-0053 | C54: Group | D54: Shared Experience | E54: Office Outing | F54: Venue | G54: Expense | H54: 46247 | I54: 0.049456019 | J54: 46247.049 | K54: 4138 | L54: INR | M54: -4138 | N54: IOS Meera | O54: 3 | P54: PERCENTAGE | Q54: MAESTRO-IOS-GROUP-OFFICE_OUTING-0053 | Venue | 4138.00 | R54: iPhone | S54: B02 | T54: BASELINE_1_500 | U54: CREATED | V54: idem-20260902-ios-0053
A55: 54 | B55: MTR-IOS-0054 | C55: Business | D55: Business | E55: Business Operations | F55: Accounting | G55: Expense | H55: 46064 | I55: 0.91460648 | J55: 46064.915 | K55: 56575.85 | L55: INR | M55: -56575.85 | N55: IOS Owner | Q55: MAESTRO-IOS-BUSINESS-BUSINESS_OPERATIONS-0054 | Accounting | 56575.85 | R55: iPhone | S55: B02 | T55: BASELINE_1_500 | U55: CREATED | V55: idem-20260902-ios-0054
A56: 55 | B56: MTR-IOS-0055 | C56: Personal | D56: Personal | E56: Relationships | F56: Gifts | G56: Expense | H56: 45997 | I56: 0.74148148 | J56: 45997.741 | K56: 11894.24 | L56: INR | M56: -11894.24 | N56: IOS Owner | Q56: MAESTRO-IOS-PERSONAL-RELATIONSHIPS-0055 | Gifts | 11894.24 | R56: iPhone | S56: B02 | T56: BASELINE_1_500 | U56: CREATED | V56: idem-20260902-ios-0055
A57: 56 | B57: MTR-IOS-0056 | C57: Group | D57: Shared Experience | E57: Office Outing | F57: Other | G57: Expense | H57: 46050 | I57: 0.81784722 | J57: 46050.818 | K57: 2675.67 | L57: INR | M57: -2675.67 | N57: IOS Owner | O57: 3 | P57: EXACT | Q57: MAESTRO-IOS-GROUP-OFFICE_OUTING-0056 | Other | 2675.67 | R57: iPhone | S57: B02 | T57: BASELINE_1_500 | U57: CREATED | V57: idem-20260902-ios-0056
A58: 57 | B58: MTR-IOS-0057 | C58: Business | D58: Business | E58: Business Operations | F58: Equipment | G58: Expense | H58: 46119 | I58: 0.86260417 | J58: 46119.863 | K58: 133277.16 | L58: INR | M58: -133277.16 | N58: IOS Owner | Q58: MAESTRO-IOS-BUSINESS-BUSINESS_OPERATIONS-0057 | Equipment | 133277.16 | R58: iPhone | S58: B02 | T58: BASELINE_1_500 | U58: CREATED | V58: idem-20260902-ios-0057
A59: 58 | B59: MTR-IOS-0058 | C59: Personal | D59: Personal | E59: Relationships | F59: Dates | G59: Expense | H59: 46098 | I59: 0.97777778 | J59: 46098.978 | K59: 9526.28 | L59: INR | M59: -9526.28 | N59: IOS Owner | Q59: MAESTRO-IOS-PERSONAL-RELATIONSHIPS-0058 | Dates | 9526.28 | R59: iPhone | S59: B02 | T59: BASELINE_1_500 | U59: CREATED | V59: idem-20260902-ios-0058
A60: 59 | B60: MTR-IOS-0059 | C60: Group | D60: Shared Experience | E60: House Party | F60: Food | G60: Expense | H60: 46083 | I60: 0.016041667 | J60: 46083.016 | K60: 645.28 | L60: INR | M60: -645.28 | N60: IOS Aarav | O60: 3 | P60: SHARES | Q60: MAESTRO-IOS-GROUP-HOUSE_PARTY-0059 | Food | 645.28 | R60: iPhone | S60: B02 | T60: BASELINE_1_500 | U60: CREATED | V60: idem-20260902-ios-0059
A61: 60 | B61: MTR-IOS-0060 | C61: Business | D61: Business | E61: Business Operations | F61: Vendor | G61: Expense | H61: 45974 | I61: 0.30393519 | J61: 45974.304 | K61: 56257.61 | L61: INR | M61: -56257.61 | N61: IOS Owner | Q61: MAESTRO-IOS-BUSINESS-BUSINESS_OPERATIONS-0060 | Vendor | 56257.61 | R61: iPhone | S61: B02 | T61: BASELINE_1_500 | U61: CREATED | V61: idem-20260902-ios-0060
A62: 61 | B62: MTR-IOS-0061 | C62: Personal | D62: Personal | E62: Relationships | F62: Family | G62: Expense | H62: 45999 | I62: 0.16987269 | J62: 45999.17 | K62: 15808.23 | L62: INR | M62: -15808.23 | N62: IOS Owner | Q62: MAESTRO-IOS-PERSONAL-RELATIONSHIPS-0061 | Family | 15808.23 | R62: iPhone | S62: B02 | T62: BASELINE_1_500 | U62: CREATED | V62: idem-20260902-ios-0061
A63: 62 | B63: MTR-IOS-0062 | C63: Group | D63: Shared Experience | E63: House Party | F63: Drinks | G63: Expense | H63: 46101 | I63: 0.40263889 | J63: 46101.403 | K63: 16257.19 | L63: INR | M63: -16257.19 | N63: IOS Meera | O63: 3 | P63: EQUAL | Q63: MAESTRO-IOS-GROUP-HOUSE_PARTY-0062 | Drinks | 16257.19 | R63: iPhone | S63: B02 | T63: BASELINE_1_500 | U63: CREATED | V63: idem-20260902-ios-0062
A64: 63 | B64: MTR-IOS-0063 | C64: Business | D64: Business | E64: Business Operations | F64: Tax | G64: Expense | H64: 46120 | I64: 0.68734954 | J64: 46120.687 | K64: 139365.36 | L64: INR | M64: -139365.36 | N64: IOS Owner | Q64: MAESTRO-IOS-BUSINESS-BUSINESS_OPERATIONS-0063 | Tax | 139365.36 | R64: iPhone | S64: B02 | T64: BASELINE_1_500 | U64: CREATED | V64: idem-20260902-ios-0063
A65: 64 | B65: MTR-IOS-0064 | C65: Personal | D65: Personal | E65: Relationships | F65: Friends | G65: Expense | H65: 45961 | I65: 0.80688657 | J65: 45961.807 | K65: 14580.17 | L65: INR | M65: -14580.17 | N65: IOS Owner | Q65: MAESTRO-IOS-PERSONAL-RELATIONSHIPS-0064 | Friends | 14580.17 | R65: iPhone | S65: B02 | T65: BASELINE_1_500 | U65: CREATED | V65: idem-20260902-ios-0064
A66: 65 | B66: MTR-IOS-0065 | C66: Group | D66: Shared Experience | E66: House Party | F66: Decor | G66: Expense | H66: 46142 | I66: 0.35289352 | J66: 46142.353 | K66: 6500.81 | L66: INR | M66: -6500.81 | N66: IOS Owner | O66: 3 | P66: PERCENTAGE | Q66: MAESTRO-IOS-GROUP-HOUSE_PARTY-0065 | Decor | 6500.81 | R66: iPhone | S66: B02 | T66: BASELINE_1_500 | U66: CREATED | V66: idem-20260902-ios-0065
A67: 66 | B67: MTR-IOS-0066 | C67: Business | D67: Business | E67: Team Operations | F67: Payroll | G67: Expense | H67: 46262 | I67: 0.70459491 | J67: 46262.705 | K67: 113953.26 | L67: INR | M67: -113953.26 | N67: IOS Owner | Q67: MAESTRO-IOS-BUSINESS-TEAM_OPERATIONS-0066 | Payroll | 113953.26 | R67: iPhone | S67: B02 | T67: BASELINE_1_500 | U67: CREATED | V67: idem-20260902-ios-0066
A68: 67 | B68: MTR-IOS-0067 | C68: Personal | D68: Personal | E68: Relationships | F68: Celebrations | G68: Expense | H68: 46044 | I68: 0.11810185 | J68: 46044.118 | K68: 9094.31 | L68: INR | M68: -9094.31 | N68: IOS Owner | Q68: MAESTRO-IOS-PERSONAL-RELATIONSHIPS-0067 | Celebrations | 9094.31 | R68: iPhone | S68: B02 | T68: BASELINE_1_500 | U68: CREATED | V68: idem-20260902-ios-0067
A69: 68 | B69: MTR-IOS-0068 | C69: Group | D69: Shared Experience | E69: House Party | F69: Supplies | G69: Expense | H69: 45904 | I69: 0.13986111 | J69: 45904.14 | K69: 12595.83 | L69: INR | M69: -12595.83 | N69: IOS Aarav | O69: 3 | P69: EXACT | Q69: MAESTRO-IOS-GROUP-HOUSE_PARTY-0068 | Supplies | 12595.83 | R69: iPhone | S69: B02 | T69: BASELINE_1_500 | U69: CREATED | V69: idem-20260902-ios-0068
A70: 69 | B70: MTR-IOS-0069 | C70: Business | D70: Business | E70: Team Operations | F70: Contractor | G70: Expense | H70: 46162 | I70: 0.33956019 | J70: 46162.34 | K70: 136731.74 | L70: INR | M70: -136731.74 | N70: IOS Owner | Q70: MAESTRO-IOS-BUSINESS-TEAM_OPERATIONS-0069 | Contractor | 136731.74 | R70: iPhone | S70: B02 | T70: BASELINE_1_500 | U70: CREATED | V70: idem-20260902-ios-0069
A71: 70 | B71: MTR-IOS-0070 | C71: Personal | D71: Personal | E71: Life Operations | F71: Groceries | G71: Expense | H71: 46139 | I71: 0.28038194 | J71: 46139.28 | K71: 1050.87 | L71: INR | M71: -1050.87 | N71: IOS Owner | Q71: MAESTRO-IOS-PERSONAL-LIFE_OPERATIONS-0070 | Groceries | 1050.87 | R71: iPhone | S71: B02 | T71: BASELINE_1_500 | U71: CREATED | V71: idem-20260902-ios-0070
A72: 71 | B72: MTR-IOS-0071 | C72: Group | D72: Shared Experience | E72: House Party | F72: Other | G72: Expense | H72: 46235 | I72: 0.65869213 | J72: 46235.659 | K72: 22932.1 | L72: INR | M72: -22932.1 | N72: IOS Meera | O72: 3 | P72: SHARES | Q72: MAESTRO-IOS-GROUP-HOUSE_PARTY-0071 | Other | 22932.10 | R72: iPhone | S72: B02 | T72: BASELINE_1_500 | U72: CREATED | V72: idem-20260902-ios-0071
A73: 72 | B73: MTR-IOS-0072 | C73: Business | D73: Business | E73: Team Operations | F73: Hiring | G73: Expense | H73: 46131 | I73: 0.57834491 | J73: 46131.578 | K73: 101440.72 | L73: INR | M73: -101440.72 | N73: IOS Owner | Q73: MAESTRO-IOS-BUSINESS-TEAM_OPERATIONS-0072 | Hiring | 101440.72 | R73: iPhone | S73: B02 | T73: BASELINE_1_500 | U73: CREATED | V73: idem-20260902-ios-0072
A74: 73 | B74: MTR-IOS-0073 | C74: Personal | D74: Personal | E74: Life Operations | F74: Rent | G74: Expense | H74: 46237 | I74: 0.74211806 | J74: 46237.742 | K74: 2637.28 | L74: INR | M74: -2637.28 | N74: IOS Owner | Q74: MAESTRO-IOS-PERSONAL-LIFE_OPERATIONS-0073 | Rent | 2637.28 | R74: iPhone | S74: B02 | T74: BASELINE_1_500 | U74: CREATED | V74: idem-20260902-ios-0073
A75: 74 | B75: MTR-IOS-0074 | C75: Group | D75: Shared Purchase | E75: Gift Pool | F75: Contribution | G75: Contribution | H75: 46260 | I75: 0.35486111 | J75: 46260.355 | K75: 99.99 | L75: INR | M75: 99.99 | N75: IOS Owner | O75: 3 | P75: EQUAL | Q75: MAESTRO-IOS-GROUP-GIFT_POOL-0074 | Contribution | 99.99 | R75: iPhone | S75: B02 | T75: BASELINE_1_500 | U75: CREATED | V75: idem-20260902-ios-0074
A76: 75 | B76: MTR-IOS-0075 | C76: Business | D76: Business | E76: Team Operations | F76: Team Meal | G76: Expense | H76: 46148 | I76: 0.39135417 | J76: 46148.391 | K76: 31526.73 | L76: INR | M76: -31526.73 | N76: IOS Owner | Q76: MAESTRO-IOS-BUSINESS-TEAM_OPERATIONS-0075 | Team Meal | 31526.73 | R76: iPhone | S76: B02 | T76: BASELINE_1_500 | U76: CREATED | V76: idem-20260902-ios-0075
A77: 76 | B77: MTR-IOS-0076 | C77: Personal | D77: Personal | E77: Life Operations | F77: Bills | G77: Expense | H77: 46132 | I77: 0.25956019 | J77: 46132.26 | K77: 12479.77 | L77: INR | M77: -12479.77 | N77: IOS Owner | Q77: MAESTRO-IOS-PERSONAL-LIFE_OPERATIONS-0076 | Bills | 12479.77 | R77: iPhone | S77: B02 | T77: BASELINE_1_500 | U77: CREATED | V77: idem-20260902-ios-0076
A78: 77 | B78: MTR-IOS-0077 | C78: Group | D78: Shared Purchase | E78: Gift Pool | F78: Gift Purchase | G78: Expense | H78: 45952 | I78: 0.91357639 | J78: 45952.914 | K78: 10652.95 | L78: INR | M78: -10652.95 | N78: IOS Aarav | O78: 3 | P78: PERCENTAGE | Q78: MAESTRO-IOS-GROUP-GIFT_POOL-0077 | Gift Purchase | 10652.95 | R78: iPhone | S78: B02 | T78: BASELINE_1_500 | U78: CREATED | V78: idem-20260902-ios-0077
A79: 78 | B79: MTR-IOS-0078 | C79: Business | D79: Business | E79: Team Operations | F79: Travel | G79: Expense | H79: 46072 | I79: 0.82716435 | J79: 46072.827 | K79: 122605.77 | L79: INR | M79: -122605.77 | N79: IOS Owner | Q79: MAESTRO-IOS-BUSINESS-TEAM_OPERATIONS-0078 | Travel | 122605.77 | R79: iPhone | S79: B02 | T79: BASELINE_1_500 | U79: CREATED | V79: idem-20260902-ios-0078
A80: 79 | B80: MTR-IOS-0079 | C80: Personal | D80: Personal | E80: Life Operations | F80: Transport | G80: Expense | H80: 46255 | I80: 0.36445602 | J80: 46255.364 | K80: 7262.27 | L80: INR | M80: -7262.27 | N80: IOS Owner | Q80: MAESTRO-IOS-PERSONAL-LIFE_OPERATIONS-0079 | Transport | 7262.27 | R80: iPhone | S80: B02 | T80: BASELINE_1_500 | U80: CREATED | V80: idem-20260902-ios-0079
A81: 80 | B81: MTR-IOS-0080 | C81: Group | D81: Shared Purchase | E81: Gift Pool | F81: Delivery | G81: Expense | H81: 46075 | I81: 0.78059028 | J81: 46075.781 | K81: 5391.57 | L81: INR | M81: -5391.57 | N81: IOS Meera | O81: 3 | P81: EXACT | Q81: MAESTRO-IOS-GROUP-GIFT_POOL-0080 | Delivery | 5391.57 | R81: iPhone | S81: B02 | T81: BASELINE_1_500 | U81: CREATED | V81: idem-20260902-ios-0080
A82: 81 | B82: MTR-IOS-0081 | C82: Business | D82: Business | E82: Team Operations | F82: Training | G82: Expense | H82: 46022 | I82: 0.839375 | J82: 46022.839 | K82: 91592.45 | L82: INR | M82: -91592.45 | N82: IOS Owner | Q82: MAESTRO-IOS-BUSINESS-TEAM_OPERATIONS-0081 | Training | 91592.45 | R82: iPhone | S82: B02 | T82: BASELINE_1_500 | U82: CREATED | V82: idem-20260902-ios-0081
A83: 82 | B83: MTR-IOS-0082 | C83: Personal | D83: Personal | E83: Life Operations | F83: Healthcare | G83: Expense | H83: 45945 | I83: 0.88350694 | J83: 45945.884 | K83: 16572.13 | L83: INR | M83: -16572.13 | N83: IOS Owner | Q83: MAESTRO-IOS-PERSONAL-LIFE_OPERATIONS-0082 | Healthcare | 16572.13 | R83: iPhone | S83: B02 | T83: BASELINE_1_500 | U83: CREATED | V83: idem-20260902-ios-0082
A84: 83 | B84: MTR-IOS-0083 | C84: Group | D84: Shared Purchase | E84: Gift Pool | F84: Other | G84: Expense | H84: 46248 | I84: 0.019502315 | J84: 46248.02 | K84: 22439.56 | L84: INR | M84: -22439.56 | N84: IOS Owner | O84: 3 | P84: SHARES | Q84: MAESTRO-IOS-GROUP-GIFT_POOL-0083 | Other | 22439.56 | R84: iPhone | S84: B02 | T84: BASELINE_1_500 | U84: CREATED | V84: idem-20260902-ios-0083
A85: 84 | B85: MTR-IOS-0084 | C85: Business | D85: Business | E85: Team Operations | F85: Tools | G85: Expense | H85: 45976 | I85: 0.45592593 | J85: 45976.456 | K85: 28921.75 | L85: INR | M85: -28921.75 | N85: IOS Owner | Q85: MAESTRO-IOS-BUSINESS-TEAM_OPERATIONS-0084 | Tools | 28921.75 | R85: iPhone | S85: B02 | T85: BASELINE_1_500 | U85: CREATED | V85: idem-20260902-ios-0084
A86: 85 | B86: MTR-IOS-0085 | C86: Personal | D86: Personal | E86: Life Operations | F86: Subscriptions | G86: Expense | H86: 45992 | I86: 0.60577546 | J86: 45992.606 | K86: 888.95 | L86: INR | M86: -888.95 | N86: IOS Owner | Q86: MAESTRO-IOS-PERSONAL-LIFE_OPERATIONS-0085 | Subscriptions | 888.95 | R86: iPhone | S86: B02 | T86: BASELINE_1_500 | U86: CREATED | V86: idem-20260902-ios-0085
A87: 86 | B87: MTR-IOS-0086 | C87: Group | D87: Shared Purchase | E87: Purchase | F87: Item | G87: Expense | H87: 46144 | I87: 0.85873843 | J87: 46144.859 | K87: 1987.64 | L87: INR | M87: -1987.64 | N87: IOS Aarav | O87: 3 | P87: EQUAL | Q87: MAESTRO-IOS-GROUP-PURCHASE-0086 | Item | 1987.64 | R87: iPhone | S87: B02 | T87: BASELINE_1_500 | U87: CREATED | V87: idem-20260902-ios-0086
A88: 87 | B88: MTR-IOS-0087 | C88: Business | D88: Business | E88: Business Runway | F88: Funding | G88: Income | H88: 45924 | I88: 0.70271991 | J88: 45924.703 | K88: 106112.85 | L88: INR | M88: 106112.85 | N88: IOS Owner | Q88: MAESTRO-IOS-BUSINESS-BUSINESS_RUNWAY-0087 | Funding | 106112.85 | R88: iPhone | S88: B02 | T88: BASELINE_1_500 | U88: CREATED | V88: idem-20260902-ios-0087
A89: 88 | B89: MTR-IOS-0088 | C89: Personal | D89: Personal | E89: Life Operations | F89: Repairs | G89: Expense | H89: 45905 | I89: 0.015393519 | J89: 45905.015 | K89: 508.87 | L89: INR | M89: -508.87 | N89: IOS Owner | Q89: MAESTRO-IOS-PERSONAL-LIFE_OPERATIONS-0088 | Repairs | 508.87 | R89: iPhone | S89: B02 | T89: BASELINE_1_500 | U89: CREATED | V89: idem-20260902-ios-0088
A90: 89 | B90: MTR-IOS-0089 | C90: Group | D90: Shared Purchase | E90: Purchase | F90: Shipping | G90: Expense | H90: 46011 | I90: 0.95112269 | J90: 46011.951 | K90: 8397.3 | L90: INR | M90: -8397.3 | N90: IOS Meera | O90: 3 | P90: PERCENTAGE | Q90: MAESTRO-IOS-GROUP-PURCHASE-0089 | Shipping | 8397.30 | R90: iPhone | S90: B02 | T90: BASELINE_1_500 | U90: CREATED | V90: idem-20260902-ios-0089
A91: 90 | B91: MTR-IOS-0090 | C91: Business | D91: Business | E91: Business Runway | F91: Revenue | G91: Income | H91: 46206 | I91: 0.49112269 | J91: 46206.491 | K91: 164732.5 | L91: INR | M91: 164732.5 | N91: IOS Owner | Q91: MAESTRO-IOS-BUSINESS-BUSINESS_RUNWAY-0090 | Revenue | 164732.50 | R91: iPhone | S91: B02 | T91: BASELINE_1_500 | U91: CREATED | V91: idem-20260902-ios-0090
A92: 91 | B92: MTR-IOS-0091 | C92: Personal | D92: Personal | E92: Future Building | F92: Savings | G92: Transfer | H92: 46207 | I92: 0.67403935 | J92: 46207.674 | K92: 1047.28 | L92: INR | M92: 0 | N92: IOS Owner | Q92: MAESTRO-IOS-PERSONAL-FUTURE_BUILDING-0091 | Savings | 1047.28 | R92: iPhone | S92: B02 | T92: BASELINE_1_500 | U92: CREATED | V92: idem-20260902-ios-0091
A93: 92 | B93: MTR-IOS-0092 | C93: Group | D93: Shared Purchase | E93: Purchase | F93: Tax | G93: Expense | H93: 46097 | I93: 0.24246528 | J93: 46097.242 | K93: 22954.16 | L93: INR | M93: -22954.16 | N93: IOS Owner | O93: 3 | P93: EXACT | Q93: MAESTRO-IOS-GROUP-PURCHASE-0092 | Tax | 22954.16 | R93: iPhone | S93: B02 | T93: BASELINE_1_500 | U93: CREATED | V93: idem-20260902-ios-0092
A94: 93 | B94: MTR-IOS-0093 | C94: Business | D94: Business | E94: Business Runway | F94: Burn | G94: Expense | H94: 45940 | I94: 0.90439815 | J94: 45940.904 | K94: 87834.75 | L94: INR | M94: -87834.75 | N94: IOS Owner | Q94: MAESTRO-IOS-BUSINESS-BUSINESS_RUNWAY-0093 | Burn | 87834.75 | R94: iPhone | S94: B02 | T94: BASELINE_1_500 | U94: CREATED | V94: idem-20260902-ios-0093
A95: 94 | B95: MTR-IOS-0094 | C95: Personal | D95: Personal | E95: Future Building | F95: Emergency Fund | G95: Transfer | H95: 45992 | I95: 0.51474537 | J95: 45992.515 | K95: 16467.85 | L95: INR | M95: 0 | N95: IOS Owner | Q95: MAESTRO-IOS-PERSONAL-FUTURE_BUILDING-0094 | Emergency Fund | 16467.85 | R95: iPhone | S95: B02 | T95: BASELINE_1_500 | U95: CREATED | V95: idem-20260902-ios-0094
A96: 95 | B96: MTR-IOS-0095 | C96: Group | D96: Shared Purchase | E96: Purchase | F96: Other | G96: Expense | H96: 45985 | I96: 0.54659722 | J96: 45985.547 | K96: 25633.17 | L96: INR | M96: -25633.17 | N96: IOS Aarav | O96: 3 | P96: SHARES | Q96: MAESTRO-IOS-GROUP-PURCHASE-0095 | Other | 25633.17 | R96: iPhone | S96: B02 | T96: BASELINE_1_500 | U96: CREATED | V96: idem-20260902-ios-0095
A97: 96 | B97: MTR-IOS-0096 | C97: Business | D97: Business | E97: Business Runway | F97: Reserve | G97: Transfer | H97: 45969 | I97: 0.41378472 | J97: 45969.414 | K97: 91780.94 | L97: INR | M97: 0 | N97: IOS Owner | Q97: MAESTRO-IOS-BUSINESS-BUSINESS_RUNWAY-0096 | Reserve | 91780.94 | R97: iPhone | S97: B02 | T97: BASELINE_1_500 | U97: CREATED | V97: idem-20260902-ios-0096
A98: 97 | B98: MTR-IOS-0097 | C98: Personal | D98: Personal | E98: Future Building | F98: Investments | G98: Investment | H98: 46165 | I98: 0.16127315 | J98: 46165.161 | K98: 14426.24 | L98: INR | M98: 0 | N98: IOS Owner | Q98: MAESTRO-IOS-PERSONAL-FUTURE_BUILDING-0097 | Investments | 14426.24 | R98: iPhone | S98: B02 | T98: BASELINE_1_500 | U98: CREATED | V98: idem-20260902-ios-0097
A99: 98 | B99: MTR-IOS-0098 | C99: Group | D99: Shared Purchase | E99: Assets | F99: Purchase | G99: Expense | H99: 46163 | I99: 0.99990741 | J99: 46164 | K99: 20917.42 | L99: INR | M99: -20917.42 | N99: IOS Meera | O99: 3 | P99: EQUAL | Q99: MAESTRO-IOS-GROUP-ASSETS-0098 | Purchase | 20917.42 | R99: iPhone | S99: B02 | T99: BASELINE_1_500 | U99: CREATED | V99: idem-20260902-ios-0098
A100: 99 | B100: MTR-IOS-0099 | C100: Business | D100: Business | E100: Business Runway | F100: Loan | G100: Income | H100: 46114 | I100: 0.79204861 | J100: 46114.792 | K100: 9873.35 | L100: INR | M100: 9873.35 | N100: IOS Owner | Q100: MAESTRO-IOS-BUSINESS-BUSINESS_RUNWAY-0099 | Loan | 9873.35 | R100: iPhone | S100: B02 | T100: BASELINE_1_500 | U100: CREATED | V100: idem-20260902-ios-0099
...

Sheet Group_Splits
A1: Txn_ID | B1: Moment | C1: Split_Method | D1: Member | E1: Paid_Amount | F1: Share_Amount | G1: Share_Percent | H1: Expected_Net | I1: Split_Check
A2: MTR-IOS-0002 | B2: Trip | C2: EQUAL | D2: IOS Owner | E2: 26868.32 | F2: 8956.11 | H2: 17912.21 | I2: 0
A3: MTR-IOS-0002 | B3: Trip | C3: EQUAL | D3: IOS Aarav | E3: 0 | F3: 8956.11 | H3: -8956.11 | I3: 0
A4: MTR-IOS-0002 | B4: Trip | C4: EQUAL | D4: IOS Meera | E4: 0 | F4: 8956.1 | H4: -8956.1 | I4: 0
A5: MTR-IOS-0005 | B5: Trip | C5: PERCENTAGE | D5: IOS Owner | E5: 0 | F5: 9175.61 | G5: 50 | H5: -9175.61 | I5: 0
A6: MTR-IOS-0005 | B6: Trip | C6: PERCENTAGE | D6: IOS Aarav | E6: 18351.21 | F6: 5505.36 | G6: 30 | H6: 12845.85 | I6: 0
A7: MTR-IOS-0005 | B7: Trip | C7: PERCENTAGE | D7: IOS Meera | E7: 0 | F7: 3670.24 | G7: 20 | H7: -3670.24 | I7: 0
A8: MTR-IOS-0008 | B8: Trip | C8: EXACT | D8: IOS Owner | E8: 0 | F8: 8465.58 | H8: -8465.58 | I8: 0
A9: MTR-IOS-0008 | B9: Trip | C9: EXACT | D9: IOS Aarav | E9: 0 | F9: 8465.58 | H9: -8465.58 | I9: 0
A10: MTR-IOS-0008 | B10: Trip | C10: EXACT | D10: IOS Meera | E10: 25422.15 | F10: 8490.99 | H10: 16931.16 | I10: 0
A11: MTR-IOS-0011 | B11: Trip | C11: SHARES | D11: IOS Owner | E11: 20814.45 | F11: 10407.23 | H11: 10407.22 | I11: 0
A12: MTR-IOS-0011 | B12: Trip | C12: SHARES | D12: IOS Aarav | E12: 0 | F12: 6938.15 | H12: -6938.15 | I12: 0
A13: MTR-IOS-0011 | B13: Trip | C13: SHARES | D13: IOS Meera | E13: 0 | F13: 3469.07 | H13: -3469.07 | I13: 0
A14: MTR-IOS-0014 | B14: Trip | C14: EQUAL | D14: IOS Owner | E14: 0 | F14: 2861.93 | H14: -2861.93 | I14: 0
A15: MTR-IOS-0014 | B15: Trip | C15: EQUAL | D15: IOS Aarav | E15: 8585.78 | F15: 2861.93 | H15: 5723.85 | I15: 0
A16: MTR-IOS-0014 | B16: Trip | C16: EQUAL | D16: IOS Meera | E16: 0 | F16: 2861.92 | H16: -2861.92 | I16: 0
A17: MTR-IOS-0017 | B17: Trip | C17: PERCENTAGE | D17: IOS Owner | E17: 0 | F17: 7445.75 | G17: 50 | H17: -7445.75 | I17: 0
A18: MTR-IOS-0017 | B18: Trip | C18: PERCENTAGE | D18: IOS Aarav | E18: 0 | F18: 4467.45 | G18: 30 | H18: -4467.45 | I18: 0
A19: MTR-IOS-0017 | B19: Trip | C19: PERCENTAGE | D19: IOS Meera | E19: 14891.49 | F19: 2978.29 | G19: 20 | H19: 11913.2 | I19: 0
A20: MTR-IOS-0020 | B20: Trip | C20: EXACT | D20: IOS Owner | E20: 16125.67 | F20: 5369.85 | H20: 10755.82 | I20: 0
A21: MTR-IOS-0020 | B21: Trip | C21: EXACT | D21: IOS Aarav | E21: 0 | F21: 5369.85 | H21: -5369.85 | I21: 0
A22: MTR-IOS-0020 | B22: Trip | C22: EXACT | D22: IOS Meera | E22: 0 | F22: 5385.97 | H22: -5385.97 | I22: 0
A23: MTR-IOS-0023 | B23: Wedding | C23: SHARES | D23: IOS Owner | E23: 0 | F23: 12462.58 | H23: -12462.58 | I23: 0
A24: MTR-IOS-0023 | B24: Wedding | C24: SHARES | D24: IOS Aarav | E24: 24925.16 | F24: 8308.39 | H24: 16616.77 | I24: 0
A25: MTR-IOS-0023 | B25: Wedding | C25: SHARES | D25: IOS Meera | E25: 0 | F25: 4154.19 | H25: -4154.19 | I25: 0
A26: MTR-IOS-0026 | B26: Wedding | C26: EQUAL | D26: IOS Owner | E26: 0 | F26: 6568.24 | H26: -6568.24 | I26: 0
A27: MTR-IOS-0026 | B27: Wedding | C27: EQUAL | D27: IOS Aarav | E27: 0 | F27: 6568.24 | H27: -6568.24 | I27: 0
A28: MTR-IOS-0026 | B28: Wedding | C28: EQUAL | D28: IOS Meera | E28: 19704.71 | F28: 6568.23 | H28: 13136.48 | I28: 0
A29: MTR-IOS-0029 | B29: Wedding | C29: PERCENTAGE | D29: IOS Owner | E29: 15620.75 | F29: 7810.38 | G29: 50 | H29: 7810.37 | I29: 0
A30: MTR-IOS-0029 | B30: Wedding | C30: PERCENTAGE | D30: IOS Aarav | E30: 0 | F30: 4686.23 | G30: 30 | H30: -4686.23 | I30: 0
A31: MTR-IOS-0029 | B31: Wedding | C31: PERCENTAGE | D31: IOS Meera | E31: 0 | F31: 3124.14 | G31: 20 | H31: -3124.14 | I31: 0
A32: MTR-IOS-0032 | B32: Wedding | C32: EXACT | D32: IOS Owner | E32: 0 | F32: 5485.38 | H32: -5485.38 | I32: 0
A33: MTR-IOS-0032 | B33: Wedding | C33: EXACT | D33: IOS Aarav | E33: 16472.62 | F33: 5485.38 | H33: 10987.24 | I33: 0
A34: MTR-IOS-0032 | B34: Wedding | C34: EXACT | D34: IOS Meera | E34: 0 | F34: 5501.86 | H34: -5501.86 | I34: 0
A35: MTR-IOS-0035 | B35: Wedding | C35: SHARES | D35: IOS Owner | E35: 0 | F35: 9410.98 | H35: -9410.98 | I35: 0
A36: MTR-IOS-0035 | B36: Wedding | C36: SHARES | D36: IOS Aarav | E36: 0 | F36: 6273.99 | H36: -6273.99 | I36: 0
A37: MTR-IOS-0035 | B37: Wedding | C37: SHARES | D37: IOS Meera | E37: 18821.96 | F37: 3136.99 | H37: 15684.97 | I37: 0
A38: MTR-IOS-0038 | B38: Wedding | C38: EQUAL | D38: IOS Owner | E38: 6824.65 | F38: 2274.88 | H38: 4549.77 | I38: 0
A39: MTR-IOS-0038 | B39: Wedding | C39: EQUAL | D39: IOS Aarav | E39: 0 | F39: 2274.88 | H39: -2274.88 | I39: 0
A40: MTR-IOS-0038 | B40: Wedding | C40: EQUAL | D40: IOS Meera | E40: 0 | F40: 2274.89 | H40: -2274.89 | I40: 0
A41: MTR-IOS-0041 | B41: Wedding | C41: PERCENTAGE | D41: IOS Owner | E41: 0 | F41: 9196.2 | G41: 50 | H41: -9196.2 | I41: 0
A42: MTR-IOS-0041 | B42: Wedding | C42: PERCENTAGE | D42: IOS Aarav | E42: 18392.39 | F42: 5517.72 | G42: 30 | H42: 12874.67 | I42: 0
A43: MTR-IOS-0041 | B43: Wedding | C43: PERCENTAGE | D43: IOS Meera | E43: 0 | F43: 3678.47 | G43: 20 | H43: -3678.47 | I43: 0
A44: MTR-IOS-0044 | B44: Office Outing | C44: EXACT | D44: IOS Owner | E44: 0 | F44: 8017.2 | H44: -8017.2 | I44: 0
A45: MTR-IOS-0044 | B45: Office Outing | C45: EXACT | D45: IOS Aarav | E45: 0 | F45: 8017.2 | H45: -8017.2 | I45: 0
A46: MTR-IOS-0044 | B46: Office Outing | C46: EXACT | D46: IOS Meera | E46: 24075.67 | F46: 8041.27 | H46: 16034.4 | I46: 0
A47: MTR-IOS-0047 | B47: Office Outing | C47: SHARES | D47: IOS Owner | E47: 26939.54 | F47: 13469.77 | H47: 13469.77 | I47: 0
A48: MTR-IOS-0047 | B48: Office Outing | C48: SHARES | D48: IOS Aarav | E48: 0 | F48: 8979.85 | H48: -8979.85 | I48: 0
A49: MTR-IOS-0047 | B49: Office Outing | C49: SHARES | D49: IOS Meera | E49: 0 | F49: 4489.92 | H49: -4489.92 | I49: 0
A50: MTR-IOS-0050 | B50: Office Outing | C50: EQUAL | D50: IOS Owner | E50: 0 | F50: 7976.36 | H50: -7976.36 | I50: 0
A51: MTR-IOS-0050 | B51: Office Outing | C51: EQUAL | D51: IOS Aarav | E51: 23929.09 | F51: 7976.36 | H51: 15952.73 | I51: 0
A52: MTR-IOS-0050 | B52: Office Outing | C52: EQUAL | D52: IOS Meera | E52: 0 | F52: 7976.37 | H52: -7976.37 | I52: 0
A53: MTR-IOS-0053 | B53: Office Outing | C53: PERCENTAGE | D53: IOS Owner | E53: 0 | F53: 2069 | G53: 50 | H53: -2069 | I53: 0
A54: MTR-IOS-0053 | B54: Office Outing | C54: PERCENTAGE | D54: IOS Aarav | E54: 0 | F54: 1241.4 | G54: 30 | H54: -1241.4 | I54: 0
A55: MTR-IOS-0053 | B55: Office Outing | C55: PERCENTAGE | D55: IOS Meera | E55: 4138 | F55: 827.6 | G55: 20 | H55: 3310.4 | I55: 0
A56: MTR-IOS-0056 | B56: Office Outing | C56: EXACT | D56: IOS Owner | E56: 2675.67 | F56: 891 | H56: 1784.67 | I56: 0
A57: MTR-IOS-0056 | B57: Office Outing | C57: EXACT | D57: IOS Aarav | E57: 0 | F57: 891 | H57: -891 | I57: 0
A58: MTR-IOS-0056 | B58: Office Outing | C58: EXACT | D58: IOS Meera | E58: 0 | F58: 893.67 | H58: -893.67 | I58: 0
A59: MTR-IOS-0059 | B59: House Party | C59: SHARES | D59: IOS Owner | E59: 0 | F59: 322.64 | H59: -322.64 | I59: 0
A60: MTR-IOS-0059 | B60: House Party | C60: SHARES | D60: IOS Aarav | E60: 645.28 | F60: 215.09 | H60: 430.19 | I60: 0
A61: MTR-IOS-0059 | B61: House Party | C61: SHARES | D61: IOS Meera | E61: 0 | F61: 107.55 | H61: -107.55 | I61: 0
A62: MTR-IOS-0062 | B62: House Party | C62: EQUAL | D62: IOS Owner | E62: 0 | F62: 5419.06 | H62: -5419.06 | I62: 0
A63: MTR-IOS-0062 | B63: House Party | C63: EQUAL | D63: IOS Aarav | E63: 0 | F63: 5419.06 | H63: -5419.06 | I63: 0
A64: MTR-IOS-0062 | B64: House Party | C64: EQUAL | D64: IOS Meera | E64: 16257.19 | F64: 5419.07 | H64: 10838.12 | I64: 0
A65: MTR-IOS-0065 | B65: House Party | C65: PERCENTAGE | D65: IOS Owner | E65: 6500.81 | F65: 3250.41 | G65: 50 | H65: 3250.4 | I65: 0
A66: MTR-IOS-0065 | B66: House Party | C66: PERCENTAGE | D66: IOS Aarav | E66: 0 | F66: 1950.24 | G66: 30 | H66: -1950.24 | I66: 0
A67: MTR-IOS-0065 | B67: House Party | C67: PERCENTAGE | D67: IOS Meera | E67: 0 | F67: 1300.16 | G67: 20 | H67: -1300.16 | I67: 0
A68: MTR-IOS-0068 | B68: House Party | C68: EXACT | D68: IOS Owner | E68: 0 | F68: 4194.41 | H68: -4194.41 | I68: 0
A69: MTR-IOS-0068 | B69: House Party | C69: EXACT | D69: IOS Aarav | E69: 12595.83 | F69: 4194.41 | H69: 8401.42 | I69: 0
A70: MTR-IOS-0068 | B70: House Party | C70: EXACT | D70: IOS Meera | E70: 0 | F70: 4207.01 | H70: -4207.01 | I70: 0
A71: MTR-IOS-0071 | B71: House Party | C71: SHARES | D71: IOS Owner | E71: 0 | F71: 11466.05 | H71: -11466.05 | I71: 0
A72: MTR-IOS-0071 | B72: House Party | C72: SHARES | D72: IOS Aarav | E72: 0 | F72: 7644.03 | H72: -7644.03 | I72: 0
A73: MTR-IOS-0071 | B73: House Party | C73: SHARES | D73: IOS Meera | E73: 22932.1 | F73: 3822.02 | H73: 19110.08 | I73: 0
A74: MTR-IOS-0074 | B74: Gift Pool | C74: EQUAL | D74: IOS Owner | E74: 99.99 | F74: 33.33 | H74: 66.66 | I74: 0
A75: MTR-IOS-0074 | B75: Gift Pool | C75: EQUAL | D75: IOS Aarav | E75: 0 | F75: 33.33 | H75: -33.33 | I75: 0
A76: MTR-IOS-0074 | B76: Gift Pool | C76: EQUAL | D76: IOS Meera | E76: 0 | F76: 33.33 | H76: -33.33 | I76: 0
A77: MTR-IOS-0077 | B77: Gift Pool | C77: PERCENTAGE | D77: IOS Owner | E77: 0 | F77: 5326.48 | G77: 50 | H77: -5326.48 | I77: 0
A78: MTR-IOS-0077 | B78: Gift Pool | C78: PERCENTAGE | D78: IOS Aarav | E78: 10652.95 | F78: 3195.89 | G78: 30 | H78: 7457.06 | I78: 0
A79: MTR-IOS-0077 | B79: Gift Pool | C79: PERCENTAGE | D79: IOS Meera | E79: 0 | F79: 2130.58 | G79: 20 | H79: -2130.58 | I79: 0
A80: MTR-IOS-0080 | B80: Gift Pool | C80: EXACT | D80: IOS Owner | E80: 0 | F80: 1795.39 | H80: -1795.39 | I80: 0
A81: MTR-IOS-0080 | B81: Gift Pool | C81: EXACT | D81: IOS Aarav | E81: 0 | F81: 1795.39 | H81: -1795.39 | I81: 0
A82: MTR-IOS-0080 | B82: Gift Pool | C82: EXACT | D82: IOS Meera | E82: 5391.57 | F82: 1800.79 | H82: 3590.78 | I82: 0
A83: MTR-IOS-0083 | B83: Gift Pool | C83: SHARES | D83: IOS Owner | E83: 22439.56 | F83: 11219.78 | H83: 11219.78 | I83: 0
A84: MTR-IOS-0083 | B84: Gift Pool | C84: SHARES | D84: IOS Aarav | E84: 0 | F84: 7479.85 | H84: -7479.85 | I84: 0
A85: MTR-IOS-0083 | B85: Gift Pool | C85: SHARES | D85: IOS Meera | E85: 0 | F85: 3739.93 | H85: -3739.93 | I85: 0
A86: MTR-IOS-0086 | B86: Purchase | C86: EQUAL | D86: IOS Owner | E86: 0 | F86: 662.55 | H86: -662.55 | I86: 0
A87: MTR-IOS-0086 | B87: Purchase | C87: EQUAL | D87: IOS Aarav | E87: 1987.64 | F87: 662.55 | H87: 1325.09 | I87: 0
A88: MTR-IOS-0086 | B88: Purchase | C88: EQUAL | D88: IOS Meera | E88: 0 | F88: 662.54 | H88: -662.54 | I88: 0
A89: MTR-IOS-0089 | B89: Purchase | C89: PERCENTAGE | D89: IOS Owner | E89: 0 | F89: 4198.65 | G89: 50 | H89: -4198.65 | I89: 0
A90: MTR-IOS-0089 | B90: Purchase | C90: PERCENTAGE | D90: IOS Aarav | E90: 0 | F90: 2519.19 | G90: 30 | H90: -2519.19 | I90: 0
A91: MTR-IOS-0089 | B91: Purchase | C91: PERCENTAGE | D91: IOS Meera | E91: 8397.3 | F91: 1679.46 | G91: 20 | H91: 6717.84 | I91: 0
A92: MTR-IOS-0092 | B92: Purchase | C92: EXACT | D92: IOS Owner | E92: 22954.16 | F92: 7643.74 | H92: 15310.42 | I92: 0
A93: MTR-IOS-0092 | B93: Purchase | C93: EXACT | D93: IOS Aarav | E93: 0 | F93: 7643.74 | H93: -7643.74 | I93: 0
A94: MTR-IOS-0092 | B94: Purchase | C94: EXACT | D94: IOS Meera | E94: 0 | F94: 7666.68 | H94: -7666.68 | I94: 0
A95: MTR-IOS-0095 | B95: Purchase | C95: SHARES | D95: IOS Owner | E95: 0 | F95: 12816.59 | H95: -12816.59 | I95: 0
A96: MTR-IOS-0095 | B96: Purchase | C96: SHARES | D96: IOS Aarav | E96: 25633.17 | F96: 8544.39 | H96: 17088.78 | I96: 0
A97: MTR-IOS-0095 | B97: Purchase | C97: SHARES | D97: IOS Meera | E97: 0 | F97: 4272.19 | H97: -4272.19 | I97: 0
A98: MTR-IOS-0098 | B98: Assets | C98: EQUAL | D98: IOS Owner | E98: 0 | F98: 6972.47 | H98: -6972.47 | I98: 0
A99: MTR-IOS-0098 | B99: Assets | C99: EQUAL | D99: IOS Aarav | E99: 0 | F99: 6972.47 | H99: -6972.47 | I99: 0
A100: MTR-IOS-0098 | B100: Assets | C100: EQUAL | D100: IOS Meera | E100: 20917.42 | F100: 6972.48 | H100: 13944.94 | I100: 0
...

Sheet Expected_Summary
A1: Mode | B1: Family | C1: Moment | D1: Quick_Add | E1: Expected_Count | F1: Expected_Gross_Amount | G1: Expected_Positive | H1: Expected_Expense_Absolute | I1: Expected_Net | J1: Count_Check
A2: Personal | B2: Personal | C2: Life Operations | D2: Groceries | E2: =COUNTIFS(Transactions!$C:$C,A2,Transactions!$D:$D,B2,Transactions!$E:$E,C2,Transactions!$F:$F,D2) | F2: =SUMIFS(Transactions!$K:$K,Transactions!$C:$C,A2,Transactions!$D:$D,B2,Transactions!$E:$E,C2,Transactions!$F:$F,D2) | G2: =SUMIFS(Transactions!$M:$M,Transactions!$C:$C,A2,Transactions!$D:$D,B2,Transactions!$E:$E,C2,Transactions!$F:$F,D2,Transactions!$M:$M,">0") | H2: =-SUMIFS(Transactions!$M:$M,Transactions!$C:$C,A2,Transactions!$D:$D,B2,Transactions!$E:$E,C2,Transactions!$F:$F,D2,Transactions!$M:$M,"<0") | I2: =SUMIFS(Transactions!$M:$M,Transactions!$C:$C,A2,Transactions!$D:$D,B2,Transactions!$E:$E,C2,Transactions!$F:$F,D2) | J2: =IF(E2>0,"PASS","FAIL")
A3: Personal | B3: Personal | C3: Life Operations | D3: Rent | E3: =COUNTIFS(Transactions!$C:$C,A3,Transactions!$D:$D,B3,Transactions!$E:$E,C3,Transactions!$F:$F,D3) | F3: =SUMIFS(Transactions!$K:$K,Transactions!$C:$C,A3,Transactions!$D:$D,B3,Transactions!$E:$E,C3,Transactions!$F:$F,D3) | G3: =SUMIFS(Transactions!$M:$M,Transactions!$C:$C,A3,Transactions!$D:$D,B3,Transactions!$E:$E,C3,Transactions!$F:$F,D3,Transactions!$M:$M,">0") | H3: =-SUMIFS(Transactions!$M:$M,Transactions!$C:$C,A3,Transactions!$D:$D,B3,Transactions!$E:$E,C3,Transactions!$F:$F,D3,Transactions!$M:$M,"<0") | I3: =SUMIFS(Transactions!$M:$M,Transactions!$C:$C,A3,Transactions!$D:$D,B3,Transactions!$E:$E,C3,Transactions!$F:$F,D3) | J3: =IF(E3>0,"PASS","FAIL")
A4: Personal | B4: Personal | C4: Life Operations | D4: Bills | E4: =COUNTIFS(Transactions!$C:$C,A4,Transactions!$D:$D,B4,Transactions!$E:$E,C4,Transactions!$F:$F,D4) | F4: =SUMIFS(Transactions!$K:$K,Transactions!$C:$C,A4,Transactions!$D:$D,B4,Transactions!$E:$E,C4,Transactions!$F:$F,D4) | G4: =SUMIFS(Transactions!$M:$M,Transactions!$C:$C,A4,Transactions!$D:$D,B4,Transactions!$E:$E,C4,Transactions!$F:$F,D4,Transactions!$M:$M,">0") | H4: =-SUMIFS(Transactions!$M:$M,Transactions!$C:$C,A4,Transactions!$D:$D,B4,Transactions!$E:$E,C4,Transactions!$F:$F,D4,Transactions!$M:$M,"<0") | I4: =SUMIFS(Transactions!$M:$M,Transactions!$C:$C,A4,Transactions!$D:$D,B4,Transactions!$E:$E,C4,Transactions!$F:$F,D4) | J4: =IF(E4>0,"PASS","FAIL")
A5: Personal | B5: Personal | C5: Life Operations | D5: Transport | E5: =COUNTIFS(Transactions!$C:$C,A5,Transactions!$D:$D,B5,Transactions!$E:$E,C5,Transactions!$F:$F,D5) | F5: =SUMIFS(Transactions!$K:$K,Transactions!$C:$C,A5,Transactions!$D:$D,B5,Transactions!$E:$E,C5,Transactions!$F:$F,D5) | G5: =SUMIFS(Transactions!$M:$M,Transactions!$C:$C,A5,Transactions!$D:$D,B5,Transactions!$E:$E,C5,Transactions!$F:$F,D5,Transactions!$M:$M,">0") | H5: =-SUMIFS(Transactions!$M:$M,Transactions!$C:$C,A5,Transactions!$D:$D,B5,Transactions!$E:$E,C5,Transactions!$F:$F,D5,Transactions!$M:$M,"<0") | I5: =SUMIFS(Transactions!$M:$M,Transactions!$C:$C,A5,Transactions!$D:$D,B5,Transactions!$E:$E,C5,Transactions!$F:$F,D5) | J5: =IF(E5>0,"PASS","FAIL")
A6: Personal | B6: Personal | C6: Life Operations | D6: Healthcare | E6: =COUNTIFS(Transactions!$C:$C,A6,Transactions!$D:$D,B6,Transactions!$E:$E,C6,Transactions!$F:$F,D6) | F6: =SUMIFS(Transactions!$K:$K,Transactions!$C:$C,A6,Transactions!$D:$D,B6,Transactions!$E:$E,C6,Transactions!$F:$F,D6) | G6: =SUMIFS(Transactions!$M:$M,Transactions!$C:$C,A6,Transactions!$D:$D,B6,Transactions!$E:$E,C6,Transactions!$F:$F,D6,Transactions!$M:$M,">0") | H6: =-SUMIFS(Transactions!$M:$M,Transactions!$C:$C,A6,Transactions!$D:$D,B6,Transactions!$E:$E,C6,Transactions!$F:$F,D6,Transactions!$M:$M,"<0") | I6: =SUMIFS(Transactions!$M:$M,Transactions!$C:$C,A6,Transactions!$D:$D,B6,Transactions!$E:$E,C6,Transactions!$F:$F,D6) | J6: =IF(E6>0,"PASS","FAIL")
A7: Personal | B7: Personal | C7: Life Operations | D7: Subscriptions | E7: =COUNTIFS(Transactions!$C:$C,A7,Transactions!$D:$D,B7,Transactions!$E:$E,C7,Transactions!$F:$F,D7) | F7: =SUMIFS(Transactions!$K:$K,Transactions!$C:$C,A7,Transactions!$D:$D,B7,Transactions!$E:$E,C7,Transactions!$F:$F,D7) | G7: =SUMIFS(Transactions!$M:$M,Transactions!$C:$C,A7,Transactions!$D:$D,B7,Transactions!$E:$E,C7,Transactions!$F:$F,D7,Transactions!$M:$M,">0") | H7: =-SUMIFS(Transactions!$M:$M,Transactions!$C:$C,A7,Transactions!$D:$D,B7,Transactions!$E:$E,C7,Transactions!$F:$F,D7,Transactions!$M:$M,"<0") | I7: =SUMIFS(Transactions!$M:$M,Transactions!$C:$C,A7,Transactions!$D:$D,B7,Transactions!$E:$E,C7,Transactions!$F:$F,D7) | J7: =IF(E7>0,"PASS","FAIL")
A8: Personal | B8: Personal | C8: Life Operations | D8: Repairs | E8: =COUNTIFS(Transactions!$C:$C,A8,Transactions!$D:$D,B8,Transactions!$E:$E,C8,Transactions!$F:$F,D8) | F8: =SUMIFS(Transactions!$K:$K,Transactions!$C:$C,A8,Transactions!$D:$D,B8,Transactions!$E:$E,C8,Transactions!$F:$F,D8) | G8: =SUMIFS(Transactions!$M:$M,Transactions!$C:$C,A8,Transactions!$D:$D,B8,Transactions!$E:$E,C8,Transactions!$F:$F,D8,Transactions!$M:$M,">0") | H8: =-SUMIFS(Transactions!$M:$M,Transactions!$C:$C,A8,Transactions!$D:$D,B8,Transactions!$E:$E,C8,Transactions!$F:$F,D8,Transactions!$M:$M,"<0") | I8: =SUMIFS(Transactions!$M:$M,Transactions!$C:$C,A8,Transactions!$D:$D,B8,Transactions!$E:$E,C8,Transactions!$F:$F,D8) | J8: =IF(E8>0,"PASS","FAIL")
A9: Personal | B9: Personal | C9: Future Building | D9: Savings | E9: =COUNTIFS(Transactions!$C:$C,A9,Transactions!$D:$D,B9,Transactions!$E:$E,C9,Transactions!$F:$F,D9) | F9: =SUMIFS(Transactions!$K:$K,Transactions!$C:$C,A9,Transactions!$D:$D,B9,Transactions!$E:$E,C9,Transactions!$F:$F,D9) | G9: =SUMIFS(Transactions!$M:$M,Transactions!$C:$C,A9,Transactions!$D:$D,B9,Transactions!$E:$E,C9,Transactions!$F:$F,D9,Transactions!$M:$M,">0") | H9: =-SUMIFS(Transactions!$M:$M,Transactions!$C:$C,A9,Transactions!$D:$D,B9,Transactions!$E:$E,C9,Transactions!$F:$F,D9,Transactions!$M:$M,"<0") | I9: =SUMIFS(Transactions!$M:$M,Transactions!$C:$C,A9,Transactions!$D:$D,B9,Transactions!$E:$E,C9,Transactions!$F:$F,D9) | J9: =IF(E9>0,"PASS","FAIL")
A10: Personal | B10: Personal | C10: Future Building | D10: Emergency Fund | E10: =COUNTIFS(Transactions!$C:$C,A10,Transactions!$D:$D,B10,Transactions!$E:$E,C10,Transactions!$F:$F,D10) | F10: =SUMIFS(Transactions!$K:$K,Transactions!$C:$C,A10,Transactions!$D:$D,B10,Transactions!$E:$E,C10,Transactions!$F:$F,D10) | G10: =SUMIFS(Transactions!$M:$M,Transactions!$C:$C,A10,Transactions!$D:$D,B10,Transactions!$E:$E,C10,Transactions!$F:$F,D10,Transactions!$M:$M,">0") | H10: =-SUMIFS(Transactions!$M:$M,Transactions!$C:$C,A10,Transactions!$D:$D,B10,Transactions!$E:$E,C10,Transactions!$F:$F,D10,Transactions!$M:$M,"<0") | I10: =SUMIFS(Transactions!$M:$M,Transactions!$C:$C,A10,Transactions!$D:$D,B10,Transactions!$E:$E,C10,Transactions!$F:$F,D10) | J10: =IF(E10>0,"PASS","FAIL")
A11: Personal | B11: Personal | C11: Future Building | D11: Investments | E11: =COUNTIFS(Transactions!$C:$C,A11,Transactions!$D:$D,B11,Transactions!$E:$E,C11,Transactions!$F:$F,D11) | F11: =SUMIFS(Transactions!$K:$K,Transactions!$C:$C,A11,Transactions!$D:$D,B11,Transactions!$E:$E,C11,Transactions!$F:$F,D11) | G11: =SUMIFS(Transactions!$M:$M,Transactions!$C:$C,A11,Transactions!$D:$D,B11,Transactions!$E:$E,C11,Transactions!$F:$F,D11,Transactions!$M:$M,">0") | H11: =-SUMIFS(Transactions!$M:$M,Transactions!$C:$C,A11,Transactions!$D:$D,B11,Transactions!$E:$E,C11,Transactions!$F:$F,D11,Transactions!$M:$M,"<0") | I11: =SUMIFS(Transactions!$M:$M,Transactions!$C:$C,A11,Transactions!$D:$D,B11,Transactions!$E:$E,C11,Transactions!$F:$F,D11) | J11: =IF(E11>0,"PASS","FAIL")
A12: Personal | B12: Personal | C12: Future Building | D12: Education | E12: =COUNTIFS(Transactions!$C:$C,A12,Transactions!$D:$D,B12,Transactions!$E:$E,C12,Transactions!$F:$F,D12) | F12: =SUMIFS(Transactions!$K:$K,Transactions!$C:$C,A12,Transactions!$D:$D,B12,Transactions!$E:$E,C12,Transactions!$F:$F,D12) | G12: =SUMIFS(Transactions!$M:$M,Transactions!$C:$C,A12,Transactions!$D:$D,B12,Transactions!$E:$E,C12,Transactions!$F:$F,D12,Transactions!$M:$M,">0") | H12: =-SUMIFS(Transactions!$M:$M,Transactions!$C:$C,A12,Transactions!$D:$D,B12,Transactions!$E:$E,C12,Transactions!$F:$F,D12,Transactions!$M:$M,"<0") | I12: =SUMIFS(Transactions!$M:$M,Transactions!$C:$C,A12,Transactions!$D:$D,B12,Transactions!$E:$E,C12,Transactions!$F:$F,D12) | J12: =IF(E12>0,"PASS","FAIL")
A13: Personal | B13: Personal | C13: Future Building | D13: Goal Contribution | E13: =COUNTIFS(Transactions!$C:$C,A13,Transactions!$D:$D,B13,Transactions!$E:$E,C13,Transactions!$F:$F,D13) | F13: =SUMIFS(Transactions!$K:$K,Transactions!$C:$C,A13,Transactions!$D:$D,B13,Transactions!$E:$E,C13,Transactions!$F:$F,D13) | G13: =SUMIFS(Transactions!$M:$M,Transactions!$C:$C,A13,Transactions!$D:$D,B13,Transactions!$E:$E,C13,Transactions!$F:$F,D13,Transactions!$M:$M,">0") | H13: =-SUMIFS(Transactions!$M:$M,Transactions!$C:$C,A13,Transactions!$D:$D,B13,Transactions!$E:$E,C13,Transactions!$F:$F,D13,Transactions!$M:$M,"<0") | I13: =SUMIFS(Transactions!$M:$M,Transactions!$C:$C,A13,Transactions!$D:$D,B13,Transactions!$E:$E,C13,Transactions!$F:$F,D13) | J13: =IF(E13>0,"PASS","FAIL")
... A103: Business | B103: Business | C103: Business Operations | D103: Tax | E103: =COUNTIFS(Transactions!$C:$C,A103,Transactions!$D:$D,B103,Transactions!$E:$E,C103,Transactions!$F:$F,D103) | F103: =SUMIFS(Transactions!$K:$K,Transactions!$C:$C,A103,Transactions!$D:$D,B103,Transactions!$E:$E,C103,Transactions!$F:$F,D103) | G103: =SUMIFS(Transactions!$M:$M,Transactions!$C:$C,A103,Transactions!$D:$D,B103,Transactions!$E:$E,C103,Transactions!$F:$F,D103,Transactions!$M:$M,">0") | H103: =-SUMIFS(Transactions!$M:$M,Transactions!$C:$C,A103,Transactions!$D:$D,B103,Transactions!$E:$E,C103,Transactions!$F:$F,D103,Transactions!$M:$M,"<0") | I103: =SUMIFS(Transactions!$M:$M,Transactions!$C:$C,A103,Transactions!$D:$D,B103,Transactions!$E:$E,C103,Transactions!$F:$F,D103) | J103: =IF(E103>0,"PASS","FAIL")

Sheet Reconciliation
A1: Mode | B1: Family | C1: Moment | D1: Expected_Count | E1: Actual_Count | F1: Count_Variance | G1: Expected_Gross | H1: Actual_Gross | I1: Gross_Variance | J1: Expected_Net | K1: Actual_Net | L1: Net_Variance | M1: Tolerance | N1: Result | O1: Notes
A2: Personal | B2: Personal | C2: Life Operations | D2: =COUNTIFS(Transactions!$C:$C,A2,Transactions!$D:$D,B2,Transactions!$E:$E,C2) | F2: =IF(E2="","",E2-D2) | G2: =SUMIFS(Transactions!$K:$K,Transactions!$C:$C,A2,Transactions!$D:$D,B2,Transactions!$E:$E,C2) | I2: =IF(H2="","",H2-G2) | J2: =SUMIFS(Transactions!$M:$M,Transactions!$C:$C,A2,Transactions!$D:$D,B2,Transactions!$E:$E,C2) | L2: =IF(K2="","",K2-J2) | M2: =Config!$B$8 | N2: =IF(OR(E2="",H2="",K2=""),"PENDING",IF(AND(F2=0,ABS(I2)<=M2,ABS(L2)<=M2),"PASS","FAIL")) | O2: Paste actual values from API/UI/export
A3: Personal | B3: Personal | C3: Future Building | D3: =COUNTIFS(Transactions!$C:$C,A3,Transactions!$D:$D,B3,Transactions!$E:$E,C3) | F3: =IF(E3="","",E3-D3) | G3: =SUMIFS(Transactions!$K:$K,Transactions!$C:$C,A3,Transactions!$D:$D,B3,Transactions!$E:$E,C3) | I3: =IF(H3="","",H3-G3) | J3: =SUMIFS(Transactions!$M:$M,Transactions!$C:$C,A3,Transactions!$D:$D,B3,Transactions!$E:$E,C3) | L3: =IF(K3="","",K3-J3) | M3: =Config!$B$8 | N3: =IF(OR(E3="",H3="",K3=""),"PENDING",IF(AND(F3=0,ABS(I3)<=M3,ABS(L3)<=M3),"PASS","FAIL")) | O3: Paste actual values from API/UI/export
A4: Personal | B4: Personal | C4: Lifestyle | D4: =COUNTIFS(Transactions!$C:$C,A4,Transactions!$D:$D,B4,Transactions!$E:$E,C4) | F4: =IF(E4="","",E4-D4) | G4: =SUMIFS(Transactions!$K:$K,Transactions!$C:$C,A4,Transactions!$D:$D,B4,Transactions!$E:$E,C4) | I4: =IF(H4="","",H4-G4) | J4: =SUMIFS(Transactions!$M:$M,Transactions!$C:$C,A4,Transactions!$D:$D,B4,Transactions!$E:$E,C4) | L4: =IF(K4="","",K4-J4) | M4: =Config!$B$8 | N4: =IF(OR(E4="",H4="",K4=""),"PENDING",IF(AND(F4=0,ABS(I4)<=M4,ABS(L4)<=M4),"PASS","FAIL")) | O4: Paste actual values from API/UI/export
A5: Personal | B5: Personal | C5: Relationships | D5: =COUNTIFS(Transactions!$C:$C,A5,Transactions!$D:$D,B5,Transactions!$E:$E,C5) | F5: =IF(E5="","",E5-D5) | G5: =SUMIFS(Transactions!$K:$K,Transactions!$C:$C,A5,Transactions!$D:$D,B5,Transactions!$E:$E,C5) | I5: =IF(H5="","",H5-G5) | J5: =SUMIFS(Transactions!$M:$M,Transactions!$C:$C,A5,Transactions!$D:$D,B5,Transactions!$E:$E,C5) | L5: =IF(K5="","",K5-J5) | M5: =Config!$B$8 | N5: =IF(OR(E5="",H5="",K5=""),"PENDING",IF(AND(F5=0,ABS(I5)<=M5,ABS(L5)<=M5),"PASS","FAIL")) | O5: Paste actual values from API/UI/export
A6: Group | B6: Shared Experience | C6: Trip | D6: =COUNTIFS(Transactions!$C:$C,A6,Transactions!$D:$D,B6,Transactions!$E:$E,C6) | F6: =IF(E6="","",E6-D6) | G6: =SUMIFS(Transactions!$K:$K,Transactions!$C:$C,A6,Transactions!$D:$D,B6,Transactions!$E:$E,C6) | I6: =IF(H6="","",H6-G6) | J6: =SUMIFS(Transactions!$M:$M,Transactions!$C:$C,A6,Transactions!$D:$D,B6,Transactions!$E:$E,C6) | L6: =IF(K6="","",K6-J6) | M6: =Config!$B$8 | N6: =IF(OR(E6="",H6="",K6=""),"PENDING",IF(AND(F6=0,ABS(I6)<=M6,ABS(L6)<=M6),"PASS","FAIL")) | O6: Paste actual values from API/UI/export
A7: Group | B7: Shared Experience | C7: Wedding | D7: =COUNTIFS(Transactions!$C:$C,A7,Transactions!$D:$D,B7,Transactions!$E:$E,C7) | F7: =IF(E7="","",E7-D7) | G7: =SUMIFS(Transactions!$K:$K,Transactions!$C:$C,A7,Transactions!$D:$D,B7,Transactions!$E:$E,C7) | I7: =IF(H7="","",H7-G7) | J7: =SUMIFS(Transactions!$M:$M,Transactions!$C:$C,A7,Transactions!$D:$D,B7,Transactions!$E:$E,C7) | L7: =IF(K7="","",K7-J7) | M7: =Config!$B$8 | N7: =IF(OR(E7="",H7="",K7=""),"PENDING",IF(AND(F7=0,ABS(I7)<=M7,ABS(L7)<=M7),"PASS","FAIL")) | O7: Paste actual values from API/UI/export
A8: Group | B8: Shared Experience | C8: Office Outing | D8: =COUNTIFS(Transactions!$C:$C,A8,Transactions!$D:$D,B8,Transactions!$E:$E,C8) | F8: =IF(E8="","",E8-D8) | G8: =SUMIFS(Transactions!$K:$K,Transactions!$C:$C,A8,Transactions!$D:$D,B8,Transactions!$E:$E,C8) | I8: =IF(H8="","",H8-G8) | J8: =SUMIFS(Transactions!$M:$M,Transactions!$C:$C,A8,Transactions!$D:$D,B8,Transactions!$E:$E,C8) | L8: =IF(K8="","",K8-J8) | M8: =Config!$B$8 | N8: =IF(OR(E8="",H8="",K8=""),"PENDING",IF(AND(F8=0,ABS(I8)<=M8,ABS(L8)<=M8),"PASS","FAIL")) | O8: Paste actual values from API/UI/export
A9: Group | B9: Shared Experience | C9: House Party | D9: =COUNTIFS(Transactions!$C:$C,A9,Transactions!$D:$D,B9,Transactions!$E:$E,C9) | F9: =IF(E9="","",E9-D9) | G9: =SUMIFS(Transactions!$K:$K,Transactions!$C:$C,A9,Transactions!$D:$D,B9,Transactions!$E:$E,C9) | I9: =IF(H9="","",H9-G9) | J9: =SUMIFS(Transactions!$M:$M,Transactions!$C:$C,A9,Transactions!$D:$D,B9,Transactions!$E:$E,C9) | L9: =IF(K9="","",K9-J9) | M9: =Config!$B$8 | N9: =IF(OR(E9="",H9="",K9=""),"PENDING",IF(AND(F9=0,ABS(I9)<=M9,ABS(L9)<=M9),"PASS","FAIL")) | O9: Paste actual values from API/UI/export
A10: Group | B10: Shared Purchase | C10: Gift Pool | D10: =COUNTIFS(Transactions!$C:$C,A10,Transactions!$D:$D,B10,Transactions!$E:$E,C10) | F10: =IF(E10="","",E10-D10) | G10: =SUMIFS(Transactions!$K:$K,Transactions!$C:$C,A10,Transactions!$D:$D,B10,Transactions!$E:$E,C10) | I10: =IF(H10="","",H10-G10) | J10: =SUMIFS(Transactions!$M:$M,Transactions!$C:$C,A10,Transactions!$D:$D,B10,Transactions!$E:$E,C10) | L10: =IF(K10="","",K10-J10) | M10: =Config!$B$8 | N10: =IF(OR(E10="",H10="",K10=""),"PENDING",IF(AND(F10=0,ABS(I10)<=M10,ABS(L10)<=M10),"PASS","FAIL")) | O10: Paste actual values from API/UI/export
A11: Group | B11: Shared Purchase | C11: Purchase | D11: =COUNTIFS(Transactions!$C:$C,A11,Transactions!$D:$D,B11,Transactions!$E:$E,C11) | F11: =IF(E11="","",E11-D11) | G11: =SUMIFS(Transactions!$K:$K,Transactions!$C:$C,A11,Transactions!$D:$D,B11,Transactions!$E:$E,C11) | I11: =IF(H11="","",H11-G11) | J11: =SUMIFS(Transactions!$M:$M,Transactions!$C:$C,A11,Transactions!$D:$D,B11,Transactions!$E:$E,C11) | L11: =IF(K11="","",K11-J11) | M11: =Config!$B$8 | N11: =IF(OR(E11="",H11="",K11=""),"PENDING",IF(AND(F11=0,ABS(I11)<=M11,ABS(L11)<=M11),"PASS","FAIL")) | O11: Paste actual values from API/UI/export
A12: Group | B12: Shared Purchase | C12: Assets | D12: =COUNTIFS(Transactions!$C:$C,A12,Transactions!$D:$D,B12,Transactions!$E:$E,C12) | F12: =IF(E12="","",E12-D12) | G12: =SUMIFS(Transactions!$K:$K,Transactions!$C:$C,A12,Transactions!$D:$D,B12,Transactions!$E:$E,C12) | I12: =IF(H12="","",H12-G12) | J12: =SUMIFS(Transactions!$M:$M,Transactions!$C:$C,A12,Transactions!$D:$D,B12,Transactions!$E:$E,C12) | L12: =IF(K12="","",K12-J12) | M12: =Config!$B$8 | N12: =IF(OR(E12="",H12="",K12=""),"PENDING",IF(AND(F12=0,ABS(I12)<=M12,ABS(L12)<=M12),"PASS","FAIL")) | O12: Paste actual values from API/UI/export
A13: Group | B13: Shared Purchase | C13: Custom Purchase | D13: =COUNTIFS(Transactions!$C:$C,A13,Transactions!$D:$D,B13,Transactions!$E:$E,C13) | F13: =IF(E13="","",E13-D13) | G13: =SUMIFS(Transactions!$K:$K,Transactions!$C:$C,A13,Transactions!$D:$D,B13,Transactions!$E:$E,C13) | I13: =IF(H13="","",H13-G13) | J13: =SUMIFS(Transactions!$M:$M,Transactions!$C:$C,A13,Transactions!$D:$D,B13,Transactions!$E:$E,C13) | L13: =IF(K13="","",K13-J13) | M13: =Config!$B$8 | N13: =IF(OR(E13="",H13="",K13=""),"PENDING",IF(AND(F13=0,ABS(I13)<=M13,ABS(L13)<=M13),"PASS","FAIL")) | O13: Paste actual values from API/UI/export
... A20: Business | B20: Business | C20: Business Operations | D20: =COUNTIFS(Transactions!$C:$C,A20,Transactions!$D:$D,B20,Transactions!$E:$E,C20) | F20: =IF(E20="","",E20-D20) | G20: =SUMIFS(Transactions!$K:$K,Transactions!$C:$C,A20,Transactions!$D:$D,B20,Transactions!$E:$E,C20) | I20: =IF(H20="","",H20-G20) | J20: =SUMIFS(Transactions!$M:$M,Transactions!$C:$C,A20,Transactions!$D:$D,B20,Transactions!$E:$E,C20) | L20: =IF(K20="","",K20-J20) | M20: =Config!$B$8 | N20: =IF(OR(E20="",H20="",K20=""),"PENDING",IF(AND(F20=0,ABS(I20)<=M20,ABS(L20)<=M20),"PASS","FAIL")) | O20: Paste actual values from API/UI/export

Sheet Maestro_Run
A1: Sequence | B1: Txn_ID | C1: Device | D1: Mode | E1: Family | F1: Moment | G1: Quick_Add | H1: UI_Path | I1: Amount | J1: Expected_Assertion | K1: Run_Status | L1: UI_Duration_ms | M1: API_Duration_ms | N1: HTTP_Status | O1: Backend_Txn_ID | P1: Retry_Count | Q1: Observed_Count_After | R1: Notes
A2: 1 | B2: MTR-IOS-0001 | C2: iPhone | D2: Personal | E2: Personal | F2: Life Operations | G2: Groceries | H2: Personal > Life Operations > Quick Add > Groceries | I2: 14066.5 | J2: Created MTR-IOS-0001 and correlation note visible in Activity/Pulse | K2: NOT_RUN | P2: 0 | Q2: 1
A3: 2 | B3: MTR-IOS-0002 | C3: iPhone | D3: Group | E3: Shared Experience | F3: Trip | G3: Travel | H3: Group > Trip > Quick Add > Travel | I3: 26868.32 | J3: Created MTR-IOS-0002 and correlation note visible in Activity/Pulse | K3: NOT_RUN | P3: 0 | Q3: 2
A4: 3 | B4: MTR-IOS-0003 | C4: iPhone | D4: Business | E4: Business | F4: Team Operations | G4: Payroll | H4: Business > Team Operations > Quick Add > Payroll | I4: 57453.63 | J4: Created MTR-IOS-0003 and correlation note visible in Activity/Pulse | K4: NOT_RUN | P4: 0 | Q4: 3
A5: 4 | B5: MTR-IOS-0004 | C5: iPhone | D5: Personal | E5: Personal | F5: Life Operations | G5: Rent | H5: Personal > Life Operations > Quick Add > Rent | I5: 2414.9 | J5: Created MTR-IOS-0004 and correlation note visible in Activity/Pulse | K5: NOT_RUN | P5: 0 | Q5: 4
A6: 5 | B6: MTR-IOS-0005 | C6: iPhone | D6: Group | E6: Shared Experience | F6: Trip | G6: Stay | H6: Group > Trip > Quick Add > Stay | I6: 18351.21 | J6: Created MTR-IOS-0005 and correlation note visible in Activity/Pulse | K6: NOT_RUN | P6: 0 | Q6: 5
A7: 6 | B7: MTR-IOS-0006 | C7: iPhone | D7: Business | E7: Business | F7: Team Operations | G7: Contractor | H7: Business > Team Operations > Quick Add > Contractor | I7: 109737.08 | J7: Created MTR-IOS-0006 and correlation note visible in Activity/Pulse | K7: NOT_RUN | P7: 0 | Q7: 6
A8: 7 | B8: MTR-IOS-0007 | C8: iPhone | D8: Personal | E8: Personal | F8: Life Operations | G8: Bills | H8: Personal > Life Operations > Quick Add > Bills | I8: 7285.65 | J8: Created MTR-IOS-0007 and correlation note visible in Activity/Pulse | K8: NOT_RUN | P8: 0 | Q8: 7
A9: 8 | B9: MTR-IOS-0008 | C9: iPhone | D9: Group | E9: Shared Experience | F9: Trip | G9: Food | H9: Group > Trip > Quick Add > Food | I9: 25422.15 | J9: Created MTR-IOS-0008 and correlation note visible in Activity/Pulse | K9: NOT_RUN | P9: 0 | Q9: 8
A10: 9 | B10: MTR-IOS-0009 | C10: iPhone | D10: Business | E10: Business | F10: Team Operations | G10: Hiring | H10: Business > Team Operations > Quick Add > Hiring | I10: 142974.65 | J10: Created MTR-IOS-0009 and correlation note visible in Activity/Pulse | K10: NOT_RUN | P10: 0 | Q10: 9
A11: 10 | B11: MTR-IOS-0010 | C11: iPhone | D11: Personal | E11: Personal | F11: Life Operations | G11: Transport | H11: Personal > Life Operations > Quick Add > Transport | I11: 13838.38 | J11: Created MTR-IOS-0010 and correlation note visible in Activity/Pulse | K11: NOT_RUN | P11: 0 | Q11: 10
A12: 11 | B12: MTR-IOS-0011 | C12: iPhone | D12: Group | E12: Shared Experience | F12: Trip | G12: Local Transport | H12: Group > Trip > Quick Add > Local Transport | I12: 20814.45 | J12: Created MTR-IOS-0011 and correlation note visible in Activity/Pulse | K12: NOT_RUN | P12: 0 | Q12: 11
A13: 12 | B13: MTR-IOS-0012 | C13: iPhone | D13: Business | E13: Business | F13: Team Operations | G13: Team Meal | H13: Business > Team Operations > Quick Add > Team Meal | I13: 153816.21 | J13: Created MTR-IOS-0012 and correlation note visible in Activity/Pulse | K13: NOT_RUN | P13: 0 | Q13: 12
... A3501: 3500 | B3501: MTR-IOS-3500 | C3501: iPhone | D3501: Group | E3501: Shared Experience | F3501: Trip | G3501: Other | H3501: Group > Trip > Quick Add > Other | I3501: 21962.77 | J3501: Created MTR-IOS-3500 and correlation note visible in Activity/Pulse | K3501: NOT_RUN | P3501: 0 | Q3501: 3500

Sheet Performance_Log
A1: Checkpoint_Txns | B1: Load_Band | C1: Create_p50_ms | D1: Create_p95_ms | E1: Create_p99_ms | F1: Activity_Read_p95_ms | G1: Pulse_Refresh_p95_ms | H1: DB_Query_p95_ms | I1: Error_Count | J1: Error_Rate | K1: Create_p95_Degradation_vs_Baseline | L1: Latency_Result | M1: Error_Result | N1: Overall_Result | O1: Notes
A2: 100 | B2: BASELINE_1_500 | J2: =IF(I2="","",I2/A2) | K2: =IF(OR(D2="",$D$2=""),"",D2/$D$2-1) | L2: =IF(D2="","PENDING",IF(D2<=Config!$B$9,"PASS","FAIL")) | M2: =IF(J2="","PENDING",IF(J2<=Config!$B$12,"PASS","FAIL")) | N2: =IF(OR(L2="PENDING",M2="PENDING"),"PENDING",IF(AND(L2="PASS",M2="PASS",OR(K2="",K2<=Config!$B$11)),"PASS","FAIL"))
A3: 250 | B3: BASELINE_1_500 | J3: =IF(I3="","",I3/A3) | K3: =IF(OR(D3="",$D$2=""),"",D3/$D$2-1) | L3: =IF(D3="","PENDING",IF(D3<=Config!$B$9,"PASS","FAIL")) | M3: =IF(J3="","PENDING",IF(J3<=Config!$B$12,"PASS","FAIL")) | N3: =IF(OR(L3="PENDING",M3="PENDING"),"PENDING",IF(AND(L3="PASS",M3="PASS",OR(K3="",K3<=Config!$B$11)),"PASS","FAIL"))
A4: 500 | B4: BASELINE_1_500 | J4: =IF(I4="","",I4/A4) | K4: =IF(OR(D4="",$D$2=""),"",D4/$D$2-1) | L4: =IF(D4="","PENDING",IF(D4<=Config!$B$9,"PASS","FAIL")) | M4: =IF(J4="","PENDING",IF(J4<=Config!$B$12,"PASS","FAIL")) | N4: =IF(OR(L4="PENDING",M4="PENDING"),"PENDING",IF(AND(L4="PASS",M4="PASS",OR(K4="",K4<=Config!$B$11)),"PASS","FAIL"))
A5: 1000 | B5: RAMP_501_1500 | J5: =IF(I5="","",I5/A5) | K5: =IF(OR(D5="",$D$2=""),"",D5/$D$2-1) | L5: =IF(D5="","PENDING",IF(D5<=Config!$B$9,"PASS","FAIL")) | M5: =IF(J5="","PENDING",IF(J5<=Config!$B$12,"PASS","FAIL")) | N5: =IF(OR(L5="PENDING",M5="PENDING"),"PENDING",IF(AND(L5="PASS",M5="PASS",OR(K5="",K5<=Config!$B$11)),"PASS","FAIL"))
A6: 1500 | B6: RAMP_501_1500 | J6: =IF(I6="","",I6/A6) | K6: =IF(OR(D6="",$D$2=""),"",D6/$D$2-1) | L6: =IF(D6="","PENDING",IF(D6<=Config!$B$9,"PASS","FAIL")) | M6: =IF(J6="","PENDING",IF(J6<=Config!$B$12,"PASS","FAIL")) | N6: =IF(OR(L6="PENDING",M6="PENDING"),"PENDING",IF(AND(L6="PASS",M6="PASS",OR(K6="",K6<=Config!$B$11)),"PASS","FAIL"))
A7: 2000 | B7: RAMP_1501_2500 | J7: =IF(I7="","",I7/A7) | K7: =IF(OR(D7="",$D$2=""),"",D7/$D$2-1) | L7: =IF(D7="","PENDING",IF(D7<=Config!$B$9,"PASS","FAIL")) | M7: =IF(J7="","PENDING",IF(J7<=Config!$B$12,"PASS","FAIL")) | N7: =IF(OR(L7="PENDING",M7="PENDING"),"PENDING",IF(AND(L7="PASS",M7="PASS",OR(K7="",K7<=Config!$B$11)),"PASS","FAIL"))
A8: 2500 | B8: RAMP_1501_2500 | J8: =IF(I8="","",I8/A8) | K8: =IF(OR(D8="",$D$2=""),"",D8/$D$2-1) | L8: =IF(D8="","PENDING",IF(D8<=Config!$B$9,"PASS","FAIL")) | M8: =IF(J8="","PENDING",IF(J8<=Config!$B$12,"PASS","FAIL")) | N8: =IF(OR(L8="PENDING",M8="PENDING"),"PENDING",IF(AND(L8="PASS",M8="PASS",OR(K8="",K8<=Config!$B$11)),"PASS","FAIL"))
A9: 3000 | B9: HIGH_2501_3000 | J9: =IF(I9="","",I9/A9) | K9: =IF(OR(D9="",$D$2=""),"",D9/$D$2-1) | L9: =IF(D9="","PENDING",IF(D9<=Config!$B$9,"PASS","FAIL")) | M9: =IF(J9="","PENDING",IF(J9<=Config!$B$12,"PASS","FAIL")) | N9: =IF(OR(L9="PENDING",M9="PENDING"),"PENDING",IF(AND(L9="PASS",M9="PASS",OR(K9="",K9<=Config!$B$11)),"PASS","FAIL"))
A10: 3100 | B10: STRESS_3001_3500 | J10: =IF(I10="","",I10/A10) | K10: =IF(OR(D10="",$D$2=""),"",D10/$D$2-1) | L10: =IF(D10="","PENDING",IF(D10<=Config!$B$9,"PASS","FAIL")) | M10: =IF(J10="","PENDING",IF(J10<=Config!$B$12,"PASS","FAIL")) | N10: =IF(OR(L10="PENDING",M10="PENDING"),"PENDING",IF(AND(L10="PASS",M10="PASS",OR(K10="",K10<=Config!$B$11)),"PASS","FAIL"))
A11: 3200 | B11: STRESS_3001_3500 | J11: =IF(I11="","",I11/A11) | K11: =IF(OR(D11="",$D$2=""),"",D11/$D$2-1) | L11: =IF(D11="","PENDING",IF(D11<=Config!$B$9,"PASS","FAIL")) | M11: =IF(J11="","PENDING",IF(J11<=Config!$B$12,"PASS","FAIL")) | N11: =IF(OR(L11="PENDING",M11="PENDING"),"PENDING",IF(AND(L11="PASS",M11="PASS",OR(K11="",K11<=Config!$B$11)),"PASS","FAIL"))
A12: 3300 | B12: STRESS_3001_3500 | J12: =IF(I12="","",I12/A12) | K12: =IF(OR(D12="",$D$2=""),"",D12/$D$2-1) | L12: =IF(D12="","PENDING",IF(D12<=Config!$B$9,"PASS","FAIL")) | M12: =IF(J12="","PENDING",IF(J12<=Config!$B$12,"PASS","FAIL")) | N12: =IF(OR(L12="PENDING",M12="PENDING"),"PENDING",IF(AND(L12="PASS",M12="PASS",OR(K12="",K12<=Config!$B$11)),"PASS","FAIL"))
A13: 3400 | B13: STRESS_3001_3500 | J13: =IF(I13="","",I13/A13) | K13: =IF(OR(D13="",$D$2=""),"",D13/$D$2-1) | L13: =IF(D13="","PENDING",IF(D13<=Config!$B$9,"PASS","FAIL")) | M13: =IF(J13="","PENDING",IF(J13<=Config!$B$12,"PASS","FAIL")) | N13: =IF(OR(L13="PENDING",M13="PENDING"),"PENDING",IF(AND(L13="PASS",M13="PASS",OR(K13="",K13<=Config!$B$11)),"PASS","FAIL"))
A14: 3500 | B14: STRESS_3001_3500 | J14: =IF(I14="","",I14/A14) | K14: =IF(OR(D14="",$D$2=""),"",D14/$D$2-1) | L14: =IF(D14="","PENDING",IF(D14<=Config!$B$9,"PASS","FAIL")) | M14: =IF(J14="","PENDING",IF(J14<=Config!$B$12,"PASS","FAIL")) | N14: =IF(OR(L14="PENDING",M14="PENDING"),"PENDING",IF(AND(L14="PASS",M14="PASS",OR(K14="",K14<=Config!$B$11)),"PASS","FAIL"))

Sheet Test_Cases
A1: Test_ID | B1: Area | C1: Context | D1: Scenario | E1: Steps_Summary | F1: Expected_Result | G1: Priority | H1: Device_Coverage | I1: Data_Reference | J1: Status
A2: TC-001 | B2: Quick Add | C2: All | D2: Create one record for every QuickAdd | E2: Execute one row from every QuickAdd catalog entry | F2: Record created once; Activity/Pulse reflect expected amount | G2: P0 | H2: Android+iPhone | I2: QuickAdd_Catalog | J2: NOT_RUN
A3: TC-002 | B3: Load | C3: All | D3: 3,300 interleaved creates | E3: Run Maestro_Run in sequence | F3: No missing/duplicate records; backend remains responsive | G3: P0 | H3: Android+iPhone | I3: Transactions | J3: NOT_RUN
A4: TC-003 | B4: Performance | C4: All | D4: Compare p95 at 250 vs 3,000+ | E4: Capture metrics at each checkpoint | F4: Degradation within configured threshold | G4: P0 | H4: Android+iPhone | I4: Performance_Log | J4: NOT_RUN
A5: TC-004 | B5: Idempotency | C5: All | D5: Double tap/retry same create | E5: Submit same idempotency key twice | F5: Exactly one committed transaction | G5: P0 | H5: Android+iPhone | I5: Transactions.Idempotency_Key | J5: NOT_RUN
A6: TC-005 | B6: Offline Retry | C6: All | D6: Lose network during create | E6: Create offline/weak network then restore | F6: No duplicate; clear retry/error state | G6: P1 | H6: Android+iPhone | I6: Sample 20 rows | J6: NOT_RUN
A7: TC-006 | B7: Persistence | C7: All | D7: Kill/relaunch after batches | E7: Force stop and reopen | F7: Counts/totals persist and reload correctly | G7: P0 | H7: Android+iPhone | I7: Every 500 rows | J7: NOT_RUN
A8: TC-007 | B8: Money | C8: All | D8: Decimal rounding | E8: Use 0.01, 0.99, 10.01, 99.99 amounts | F8: No floating point drift > tolerance | G8: P0 | H8: Android+iPhone | I8: Edge rows in Transactions | J8: NOT_RUN
A9: TC-008 | B9: Money | C9: All | D9: Large amount | E9: Use 100000.00+ values | F9: No overflow/truncation/formatting error | G9: P1 | H9: Android+iPhone | I9: Edge rows in Transactions | J9: NOT_RUN
A10: TC-009 | B10: Validation | C10: All | D10: Zero/negative invalid input | E10: Try zero/negative where UI forbids it | F10: Validation shown; no backend record | G10: P1 | H10: Android+iPhone | I10: Manual edge case | J10: NOT_RUN
A11: TC-010 | B11: Group Split | C11: Group | D11: Equal split | E11: Create EQUAL split records | F11: Participant shares sum to amount within 0.01 | G11: P0 | H11: Android+iPhone | I11: Group_Splits | J11: NOT_RUN
A12: TC-011 | B12: Group Split | C12: Group | D12: Exact split | E12: Create EXACT split records | F12: Exact shares sum to amount within 0.01 | G12: P0 | H12: Android+iPhone | I12: Group_Splits | J12: NOT_RUN
... A25: TC-024 | B25: Backend | C25: All | D25: Error/retry observation | E25: Record 4xx/5xx/timeouts and retries | F25: Error rate <= configured threshold; failures explainable | G25: P0 | H25: Backend | I25: Performance_Log | J25: NOT_RUN

Sheet Dashboard
A1: Momentra Load Test Dashboard | B1: Value | D1: Context | E1: Count
A2: Planned Transactions | B2: =Config!B3 | D2: Personal | E2: 1167
A3: Personal Planned | B3: =COUNTIF(Transactions!C:C,"Personal") | D3: Group | E3: 1167
A4: Group Planned | B4: =COUNTIF(Transactions!C:C,"Group") | D4: Business | E4: 1166
A5: Business Planned | B5: =COUNTIF(Transactions!C:C,"Business")
A6: iPhone Rows | B6: =COUNTIF(Transactions!R:R,"iPhone")
A7: Other Platform Rows | B7: =3500-B6
A8: Stress 3k+ Rows | B8: =COUNTIF(Transactions!T:T,"STRESS_3001_3500")
A9: Reconciliation PASS | B9: =COUNTIF(Reconciliation!N:N,"PASS")
A10: Reconciliation FAIL | B10: =COUNTIF(Reconciliation!N:N,"FAIL")
A11: Performance PASS | B11: =COUNTIF(Performance_Log!N:N,"PASS")
A12: Performance FAIL | B12: =COUNTIF(Performance_Log!N:N,"FAIL")
